{"Id":365,"Name":"Black Lanner C","GroupName":null,"Class":"Black Lanner","Variant":"C","Tonnage":55,"BattleValue":2523,"Technology":{"Id":2,"Name":"Clan","Image":null,"SortOrder":0},"Cost":17759448,"Rules":"Standard","TROId":436,"TRO":"TR:CI","RSId":437,"RS":"RS:CI","EraIcon":"https://i.ibb.co/k6ySqKN/era03-clan-invasion.png","DateIntroduced":"3052","EraId":13,"EraStart":3050,"ImageUrl":"https://i.ibb.co/WVHNwq1/black-lanner-rg.png","IsFeatured":false,"IsPublished":true,"Release":1.00,"Type":{"Id":18,"Name":"BattleMech","Image":"BattleMech.gif","SortOrder":0},"Role":{"Id":107,"Name":"Skirmisher","Image":null,"SortOrder":5},"BFType":"BM","BFSize":2,"BFMove":"18\"","BFTMM":3,"BFArmor":5,"BFStructure":3,"BFThreshold":0,"BFDamageShort":5,"BFDamageShortMin":false,"BFDamageMedium":5,"BFDamageMediumMin":false,"BFDamageLong":0,"BFDamageLongMin":false,"BFDamageExtreme":0,"BFDamageExtemeMin":false,"BFOverheat":1,"BFPointValue":52,"BFAbilities":"CASE,OMNI","Skill":4,"FormatedTonnage":"55"}