{"Id":7476,"Name":"BattleMaster BLR-6C","GroupName":null,"Class":"BattleMaster","Variant":"BLR-6C","Tonnage":85,"BattleValue":1557,"Technology":{"Id":1,"Name":"Inner Sphere","Image":null,"SortOrder":0},"Cost":18033985,"Rules":"Advanced","TROId":539,"TRO":"RGv1","RSId":431,"RS":"RG03","EraIcon":"https://i.ibb.co/VtCdwyP/era06-republic-dark-age.png","DateIntroduced":"3081","EraId":15,"EraStart":3081,"ImageUrl":"https://i.ibb.co/Jy1FLdL/battlemaster-rg.png","IsFeatured":false,"IsPublished":true,"Release":2.00,"Type":{"Id":18,"Name":"BattleMech","Image":"BattleMech.gif","SortOrder":0},"Role":{"Id":108,"Name":"Juggernaut","Image":null,"SortOrder":3},"BFType":"BM","BFSize":4,"BFMove":"8\"","BFTMM":1,"BFArmor":8,"BFStructure":5,"BFThreshold":0,"BFDamageShort":4,"BFDamageShortMin":false,"BFDamageMedium":4,"BFDamageMediumMin":false,"BFDamageLong":0,"BFDamageLongMin":false,"BFDamageExtreme":0,"BFDamageExtemeMin":false,"BFOverheat":0,"BFPointValue":39,"BFAbilities":"AC2/2/-,CASEII,MHQ1,REAR1/1/-","Skill":4,"FormatedTonnage":"85"}