{"Units":[{"Id":7204,"Name":"Resgate PA(L) (Spotter)","GroupName":"","Class":"Resgate PA(L)","Variant":"(Spotter)","Tonnage":0.4,"BattleValue":54,"Technology":{"Id":2,"Name":"Clan","Image":null,"SortOrder":0},"Cost":2712500,"Rules":"Standard","TROId":248,"TRO":"TRVAr","RSId":409,"RS":"RS:VA","EraIcon":"https://i.ibb.co/VtCdwyP/era8-10-republic-dark-age.png","DateIntroduced":"3083","EraId":15,"EraStart":3081,"ImageUrl":"https://i.ibb.co/1zGZtZL/resgate-krise-trva.png","IsFeatured":false,"IsPublished":true,"Release":1.20,"Type":{"Id":21,"Name":"Infantry","Image":"Infantry.gif","SortOrder":3},"Role":{"Id":112,"Name":"Ambusher","Image":null,"SortOrder":1},"BFType":"BA","BFSize":1,"BFMove":"6\"j","BFTMM":0,"BFArmor":0,"BFStructure":2,"BFThreshold":0,"BFDamageShort":0,"BFDamageMedium":0,"BFDamageLong":0,"BFDamageExtreme":0,"BFOverheat":0,"BFPointValue":7,"BFAbilities":"CAR4,FR,LTAG","Skill":0,"FormatedTonnage":"0.4"},{"Id":4909,"Name":"Resgate PA(L) (Standard)","GroupName":"","Class":"Resgate PA(L)","Variant":"(Standard)","Tonnage":0.4,"BattleValue":61,"Technology":{"Id":2,"Name":"Clan","Image":null,"SortOrder":0},"Cost":3787500,"Rules":"Standard","TROId":248,"TRO":"TRVAr","RSId":409,"RS":"RS:VA","EraIcon":"https://i.ibb.co/k6ySqKN/era5-clan-invasion.png","DateIntroduced":"3059","EraId":13,"EraStart":3050,"ImageUrl":"https://i.ibb.co/1zGZtZL/resgate-krise-trva.png","IsFeatured":true,"IsPublished":true,"Release":1.20,"Type":{"Id":21,"Name":"Infantry","Image":"Infantry.gif","SortOrder":3},"Role":{"Id":112,"Name":"Ambusher","Image":null,"SortOrder":1},"BFType":"BA","BFSize":1,"BFMove":"6\"j","BFTMM":0,"BFArmor":0,"BFStructure":2,"BFThreshold":0,"BFDamageShort":0,"BFDamageMedium":0,"BFDamageLong":0,"BFDamageExtreme":0,"BFOverheat":0,"BFPointValue":11,"BFAbilities":"CAR4,FR,MEC,RCN","Skill":0,"FormatedTonnage":"0.4"},{"Id":7202,"Name":"Resgate PA(L) (Interdictor)","GroupName":"","Class":"Resgate PA(L)","Variant":"(Interdictor)","Tonnage":0.4,"BattleValue":61,"Technology":{"Id":2,"Name":"Clan","Image":null,"SortOrder":0},"Cost":2762500,"Rules":"Standard","TROId":248,"TRO":"TRVAr","RSId":409,"RS":"RS:VA","EraIcon":"https://i.ibb.co/VtCdwyP/era8-10-republic-dark-age.png","DateIntroduced":"3083","EraId":15,"EraStart":3081,"ImageUrl":"https://i.ibb.co/1zGZtZL/resgate-krise-trva.png","IsFeatured":false,"IsPublished":true,"Release":1.20,"Type":{"Id":21,"Name":"Infantry","Image":"Infantry.gif","SortOrder":3},"Role":{"Id":112,"Name":"Ambusher","Image":null,"SortOrder":1},"BFType":"BA","BFSize":1,"BFMove":"6\"j","BFTMM":0,"BFArmor":0,"BFStructure":2,"BFThreshold":0,"BFDamageShort":0,"BFDamageMedium":0,"BFDamageLong":0,"BFDamageExtreme":0,"BFOverheat":0,"BFPointValue":7,"BFAbilities":"CAR4,FR,LECM","Skill":0,"FormatedTonnage":"0.4"},{"Id":7203,"Name":"Resgate PA(L) (Scout)","GroupName":"","Class":"Resgate PA(L)","Variant":"(Scout)","Tonnage":0.4,"BattleValue":61,"Technology":{"Id":2,"Name":"Clan","Image":null,"SortOrder":0},"Cost":3512500,"Rules":"Standard","TROId":248,"TRO":"TRVAr","RSId":409,"RS":"RS:VA","EraIcon":"https://i.ibb.co/VtCdwyP/era8-10-republic-dark-age.png","DateIntroduced":"3083","EraId":15,"EraStart":3081,"ImageUrl":"https://i.ibb.co/1zGZtZL/resgate-krise-trva.png","IsFeatured":false,"IsPublished":true,"Release":1.20,"Type":{"Id":21,"Name":"Infantry","Image":"Infantry.gif","SortOrder":3},"Role":{"Id":112,"Name":"Ambusher","Image":null,"SortOrder":1},"BFType":"BA","BFSize":1,"BFMove":"6\"j","BFTMM":0,"BFArmor":0,"BFStructure":2,"BFThreshold":0,"BFDamageShort":0,"BFDamageMedium":0,"BFDamageLong":0,"BFDamageExtreme":0,"BFOverheat":0,"BFPointValue":9,"BFAbilities":"CAR4,FR,RCN","Skill":0,"FormatedTonnage":"0.4"},{"Id":7205,"Name":"Resgate PA(L) (Support)","GroupName":"","Class":"Resgate PA(L)","Variant":"(Support)","Tonnage":0.4,"BattleValue":94,"Technology":{"Id":2,"Name":"Clan","Image":null,"SortOrder":0},"Cost":2537500,"Rules":"Standard","TROId":248,"TRO":"TRVAr","RSId":409,"RS":"RS:VA","EraIcon":"https://i.ibb.co/VtCdwyP/era8-10-republic-dark-age.png","DateIntroduced":"3083","EraId":15,"EraStart":3081,"ImageUrl":"https://i.ibb.co/1zGZtZL/resgate-krise-trva.png","IsFeatured":false,"IsPublished":true,"Release":1.20,"Type":{"Id":21,"Name":"Infantry","Image":"Infantry.gif","SortOrder":3},"Role":{"Id":104,"Name":"None","Image":null,"SortOrder":0},"BFType":"BA","BFSize":1,"BFMove":"6\"j","BFTMM":0,"BFArmor":0,"BFStructure":2,"BFThreshold":0,"BFDamageShort":1,"BFDamageMedium":0,"BFDamageLong":0,"BFDamageExtreme":0,"BFOverheat":0,"BFPointValue":11,"BFAbilities":"CAR4,FR,MEC","Skill":0,"FormatedTonnage":"0.4"},{"Id":3673,"Name":"Aerie PA(L) (Salvage)","GroupName":"","Class":"Aerie PA(L)","Variant":"(Salvage)","Tonnage":0.5,"BattleValue":27,"Technology":{"Id":2,"Name":"Clan","Image":null,"SortOrder":0},"Cost":2948750,"Rules":"Standard","TROId":189,"TRO":"TR3075","RSId":396,"RS":"RS3075u-CE","EraIcon":"https://i.ibb.co/4jf2wfz/era7-jihad.png","DateIntroduced":"3069","EraId":14,"EraStart":3068,"ImageUrl":"https://i.ibb.co/mccjbL8/aerie-3075.png","IsFeatured":false,"IsPublished":true,"Release":1.30,"Type":{"Id":21,"Name":"Infantry","Image":"Infantry.gif","SortOrder":3},"Role":{"Id":112,"Name":"Ambusher","Image":null,"SortOrder":1},"BFType":"BA","BFSize":1,"BFMove":"6\"j","BFTMM":0,"BFArmor":0,"BFStructure":2,"BFThreshold":0,"BFDamageShort":0,"BFDamageMedium":0,"BFDamageLong":0,"BFDamageExtreme":0,"BFOverheat":0,"BFPointValue":7,"BFAbilities":"CAR4,SOA,STL","Skill":0,"FormatedTonnage":"0.5"},{"Id":3674,"Name":"Aerie PA(L) (Standard)","GroupName":"","Class":"Aerie PA(L)","Variant":"(Standard)","Tonnage":0.5,"BattleValue":27,"Technology":{"Id":2,"Name":"Clan","Image":null,"SortOrder":0},"Cost":2737500,"Rules":"Standard","TROId":189,"TRO":"TR3075","RSId":396,"RS":"RS3075u-CE","EraIcon":"https://i.ibb.co/QjhjKwr/era6-civil-war.png","DateIntroduced":"3067","EraId":247,"EraStart":3062,"ImageUrl":"https://i.ibb.co/mccjbL8/aerie-3075.png","IsFeatured":true,"IsPublished":true,"Release":1.30,"Type":{"Id":21,"Name":"Infantry","Image":"Infantry.gif","SortOrder":3},"Role":{"Id":112,"Name":"Ambusher","Image":null,"SortOrder":1},"BFType":"BA","BFSize":1,"BFMove":"6\"j","BFTMM":0,"BFArmor":0,"BFStructure":2,"BFThreshold":0,"BFDamageShort":0,"BFDamageMedium":0,"BFDamageLong":0,"BFDamageExtreme":0,"BFOverheat":0,"BFPointValue":7,"BFAbilities":"AM,CAR4,MEC,SOA,STL","Skill":0,"FormatedTonnage":"0.5"},{"Id":6642,"Name":"Constable Pacification Suit \u003cBase\u003e","GroupName":"","Class":"Constable Pacification Suit","Variant":"\u003cBase\u003e","Tonnage":0.75,"BattleValue":0,"Technology":{"Id":2,"Name":"Clan","Image":null,"SortOrder":0},"Cost":0,"Rules":"Standard","TROId":441,"TRO":"TR3150","RSId":192,"RS":"None","EraIcon":"https://i.ibb.co/VtCdwyP/era8-10-republic-dark-age.png","DateIntroduced":"3092","EraId":15,"EraStart":3081,"ImageUrl":"https://i.ibb.co/d0rpdK8/constable-3150.png","IsFeatured":false,"IsPublished":true,"Release":1.00,"Type":{"Id":21,"Name":"Infantry","Image":"Infantry.gif","SortOrder":3},"Role":{"Id":104,"Name":"None","Image":null,"SortOrder":0},"BFType":null,"BFSize":0,"BFMove":"","BFTMM":0,"BFArmor":0,"BFStructure":0,"BFThreshold":0,"BFDamageShort":0,"BFDamageMedium":0,"BFDamageLong":0,"BFDamageExtreme":0,"BFOverheat":0,"BFPointValue":0,"BFAbilities":"AM,CAR4,MEC","Skill":0,"FormatedTonnage":"0.8"},{"Id":5838,"Name":"Constable Pacification Suit [ECM]","GroupName":"","Class":"Constable Pacification Suit","Variant":"[ECM]","Tonnage":0.75,"BattleValue":123,"Technology":{"Id":2,"Name":"Clan","Image":null,"SortOrder":0},"Cost":0,"Rules":"Standard","TROId":441,"TRO":"TR3150","RSId":439,"RS":"RS3145u","EraIcon":"https://i.ibb.co/VtCdwyP/era8-10-republic-dark-age.png","DateIntroduced":"3092","EraId":15,"EraStart":3081,"ImageUrl":"https://i.ibb.co/d0rpdK8/constable-3150.png","IsFeatured":false,"IsPublished":true,"Release":1.00,"Type":{"Id":21,"Name":"Infantry","Image":"Infantry.gif","SortOrder":3},"Role":{"Id":112,"Name":"Ambusher","Image":null,"SortOrder":1},"BFType":"BA","BFSize":1,"BFMove":"6\"j","BFTMM":0,"BFArmor":1,"BFStructure":2,"BFThreshold":0,"BFDamageShort":1,"BFDamageMedium":0,"BFDamageLong":0,"BFDamageExtreme":0,"BFOverheat":0,"BFPointValue":10,"BFAbilities":"AM,CAR4,LECM,MEC","Skill":0,"FormatedTonnage":"0.8"},{"Id":5842,"Name":"Constable Pacification Suit [TAG]","GroupName":"","Class":"Constable Pacification Suit","Variant":"[TAG]","Tonnage":0.75,"BattleValue":123,"Technology":{"Id":2,"Name":"Clan","Image":null,"SortOrder":0},"Cost":0,"Rules":"Standard","TROId":441,"TRO":"TR3150","RSId":439,"RS":"RS3145u","EraIcon":"https://i.ibb.co/VtCdwyP/era8-10-republic-dark-age.png","DateIntroduced":"3092","EraId":15,"EraStart":3081,"ImageUrl":"https://i.ibb.co/d0rpdK8/constable-3150.png","IsFeatured":false,"IsPublished":true,"Release":1.00,"Type":{"Id":21,"Name":"Infantry","Image":"Infantry.gif","SortOrder":3},"Role":{"Id":105,"Name":"Scout","Image":null,"SortOrder":6},"BFType":"BA","BFSize":1,"BFMove":"6\"j","BFTMM":0,"BFArmor":1,"BFStructure":2,"BFThreshold":0,"BFDamageShort":1,"BFDamageMedium":0,"BFDamageLong":0,"BFDamageExtreme":0,"BFOverheat":0,"BFPointValue":10,"BFAbilities":"AM,CAR4,LTAG,MEC","Skill":0,"FormatedTonnage":"0.8"},{"Id":5841,"Name":"Constable Pacification Suit [Sensor]","GroupName":"","Class":"Constable Pacification Suit","Variant":"[Sensor]","Tonnage":0.75,"BattleValue":130,"Technology":{"Id":2,"Name":"Clan","Image":null,"SortOrder":0},"Cost":0,"Rules":"Standard","TROId":441,"TRO":"TR3150","RSId":439,"RS":"RS3145u","EraIcon":"https://i.ibb.co/VtCdwyP/era8-10-republic-dark-age.png","DateIntroduced":"3092","EraId":15,"EraStart":3081,"ImageUrl":"https://i.ibb.co/d0rpdK8/constable-3150.png","IsFeatured":false,"IsPublished":true,"Release":1.00,"Type":{"Id":21,"Name":"Infantry","Image":"Infantry.gif","SortOrder":3},"Role":{"Id":105,"Name":"Scout","Image":null,"SortOrder":6},"BFType":"BA","BFSize":1,"BFMove":"6\"j","BFTMM":0,"BFArmor":1,"BFStructure":2,"BFThreshold":0,"BFDamageShort":1,"BFDamageMedium":0,"BFDamageLong":0,"BFDamageExtreme":0,"BFOverheat":0,"BFPointValue":12,"BFAbilities":"AM,CAR4,MEC,RCN","Skill":0,"FormatedTonnage":"0.8"},{"Id":5839,"Name":"Constable Pacification Suit [LMG]","GroupName":"","Class":"Constable Pacification Suit","Variant":"[LMG]","Tonnage":0.75,"BattleValue":143,"Technology":{"Id":2,"Name":"Clan","Image":null,"SortOrder":0},"Cost":0,"Rules":"Standard","TROId":441,"TRO":"TR3150","RSId":439,"RS":"RS3145u","EraIcon":"https://i.ibb.co/VtCdwyP/era8-10-republic-dark-age.png","DateIntroduced":"3092","EraId":15,"EraStart":3081,"ImageUrl":"https://i.ibb.co/d0rpdK8/constable-3150.png","IsFeatured":false,"IsPublished":true,"Release":1.00,"Type":{"Id":21,"Name":"Infantry","Image":"Infantry.gif","SortOrder":3},"Role":{"Id":112,"Name":"Ambusher","Image":null,"SortOrder":1},"BFType":"BA","BFSize":1,"BFMove":"6\"j","BFTMM":0,"BFArmor":1,"BFStructure":2,"BFThreshold":0,"BFDamageShort":2,"BFDamageMedium":0,"BFDamageLong":0,"BFDamageExtreme":0,"BFOverheat":0,"BFPointValue":15,"BFAbilities":"AM,CAR4,MEC","Skill":0,"FormatedTonnage":"0.8"},{"Id":5840,"Name":"Constable Pacification Suit [SRM]","GroupName":"","Class":"Constable Pacification Suit","Variant":"[SRM]","Tonnage":0.75,"BattleValue":184,"Technology":{"Id":2,"Name":"Clan","Image":null,"SortOrder":0},"Cost":0,"Rules":"Standard","TROId":441,"TRO":"TR3150","RSId":439,"RS":"RS3145u","EraIcon":"https://i.ibb.co/VtCdwyP/era8-10-republic-dark-age.png","DateIntroduced":"3092","EraId":15,"EraStart":3081,"ImageUrl":"https://i.ibb.co/d0rpdK8/constable-3150.png","IsFeatured":false,"IsPublished":true,"Release":1.00,"Type":{"Id":21,"Name":"Infantry","Image":"Infantry.gif","SortOrder":3},"Role":{"Id":112,"Name":"Ambusher","Image":null,"SortOrder":1},"BFType":"BA","BFSize":1,"BFMove":"6\"j","BFTMM":0,"BFArmor":1,"BFStructure":2,"BFThreshold":0,"BFDamageShort":2,"BFDamageMedium":1,"BFDamageLong":0,"BFDamageExtreme":0,"BFOverheat":0,"BFPointValue":16,"BFAbilities":"AM,CAR4,MEC","Skill":0,"FormatedTonnage":"0.8"},{"Id":5170,"Name":"Sylph Battle Armor XR","GroupName":"","Class":"Sylph Battle Armor","Variant":"XR","Tonnage":0.75,"BattleValue":195,"Technology":{"Id":2,"Name":"Clan","Image":null,"SortOrder":0},"Cost":3807500,"Rules":"Experimental","TROId":263,"TRO":"XTRClans","RSId":263,"RS":"XTRClans","EraIcon":"https://i.ibb.co/4jf2wfz/era7-jihad.png","DateIntroduced":"3077","EraId":14,"EraStart":3068,"ImageUrl":"https://i.ibb.co/zP8FmCG/sylph-3058u.png","IsFeatured":true,"IsPublished":true,"Release":1.00,"Type":{"Id":21,"Name":"Infantry","Image":"Infantry.gif","SortOrder":3},"Role":{"Id":105,"Name":"Scout","Image":null,"SortOrder":6},"BFType":"BA","BFSize":1,"BFMove":"10\"f","BFTMM":0,"BFArmor":1,"BFStructure":2,"BFThreshold":0,"BFDamageShort":1,"BFDamageMedium":1,"BFDamageLong":0,"BFDamageExtreme":0,"BFOverheat":0,"BFPointValue":16,"BFAbilities":"AM,CAR4,MEC,SRCH","Skill":0,"FormatedTonnage":"0.8"},{"Id":3147,"Name":"Sylph Battle Armor (Upgrade)","GroupName":"","Class":"Sylph Battle Armor","Variant":"(Upgrade)","Tonnage":0.75,"BattleValue":213,"Technology":{"Id":2,"Name":"Clan","Image":null,"SortOrder":0},"Cost":3045000,"Rules":"Standard","TROId":240,"TRO":"TR3058U","RSId":255,"RS":"RS3058Uu-C","EraIcon":"https://i.ibb.co/QjhjKwr/era6-civil-war.png","DateIntroduced":"3065","EraId":247,"EraStart":3062,"ImageUrl":"https://i.ibb.co/zP8FmCG/sylph-3058u.png","IsFeatured":false,"IsPublished":true,"Release":1.00,"Type":{"Id":21,"Name":"Infantry","Image":"Infantry.gif","SortOrder":3},"Role":{"Id":105,"Name":"Scout","Image":null,"SortOrder":6},"BFType":"BA","BFSize":1,"BFMove":"10\"v","BFTMM":0,"BFArmor":1,"BFStructure":2,"BFThreshold":0,"BFDamageShort":2,"BFDamageMedium":0,"BFDamageLong":0,"BFDamageExtreme":0,"BFOverheat":0,"BFPointValue":11,"BFAbilities":"AM,ATMO,CAR4,MEC,SRCH","Skill":0,"FormatedTonnage":"0.8"},{"Id":3146,"Name":"Sylph Battle Armor (Standard)","GroupName":"","Class":"Sylph Battle Armor","Variant":"(Standard)","Tonnage":0.75,"BattleValue":280,"Technology":{"Id":2,"Name":"Clan","Image":null,"SortOrder":0},"Cost":3195000,"Rules":"Standard","TROId":240,"TRO":"TR3058U","RSId":255,"RS":"RS3058Uu-C","EraIcon":"https://i.ibb.co/k6ySqKN/era5-clan-invasion.png","DateIntroduced":"3060","EraId":13,"EraStart":3050,"ImageUrl":"https://i.ibb.co/zP8FmCG/sylph-3058u.png","IsFeatured":true,"IsPublished":true,"Release":1.00,"Type":{"Id":21,"Name":"Infantry","Image":"Infantry.gif","SortOrder":3},"Role":{"Id":105,"Name":"Scout","Image":null,"SortOrder":6},"BFType":"BA","BFSize":1,"BFMove":"10\"v","BFTMM":0,"BFArmor":1,"BFStructure":2,"BFThreshold":0,"BFDamageShort":2,"BFDamageMedium":0,"BFDamageLong":0,"BFDamageExtreme":0,"BFOverheat":0,"BFPointValue":11,"BFAbilities":"AM,ATMO,BOMB1,CAR4,MEC","Skill":0,"FormatedTonnage":"0.8"},{"Id":7919,"Name":"Elemental Battle Armor (Fire) \u003cBase\u003e","GroupName":"","Class":"Elemental Battle Armor","Variant":"(Fire) \u003cBase\u003e","Tonnage":1,"BattleValue":0,"Technology":{"Id":2,"Name":"Clan","Image":null,"SortOrder":0},"Cost":0,"Rules":"Standard","TROId":202,"TRO":"TR3085","RSId":192,"RS":"None","EraIcon":"https://i.ibb.co/4jf2wfz/era7-jihad.png","DateIntroduced":"3069","EraId":14,"EraStart":3068,"ImageUrl":"https://i.ibb.co/5TNnWM5/elemental-3058u.png","IsFeatured":false,"IsPublished":true,"Release":1.00,"Type":{"Id":21,"Name":"Infantry","Image":"Infantry.gif","SortOrder":3},"Role":{"Id":104,"Name":"None","Image":null,"SortOrder":0},"BFType":null,"BFSize":0,"BFMove":"0","BFTMM":0,"BFArmor":0,"BFStructure":0,"BFThreshold":0,"BFDamageShort":0,"BFDamageMedium":0,"BFDamageLong":0,"BFDamageExtreme":0,"BFOverheat":0,"BFPointValue":0,"BFAbilities":"0","Skill":0,"FormatedTonnage":"1"},{"Id":7920,"Name":"Elemental Battle Armor (Space) \u003cBase\u003e","GroupName":"","Class":"Elemental Battle Armor","Variant":"(Space) \u003cBase\u003e","Tonnage":1,"BattleValue":0,"Technology":{"Id":2,"Name":"Clan","Image":null,"SortOrder":0},"Cost":0,"Rules":"Standard","TROId":202,"TRO":"TR3085","RSId":192,"RS":"None","EraIcon":"https://i.ibb.co/MB09bVm/era3-4-succession-wars.png","DateIntroduced":"2903","EraId":255,"EraStart":2901,"ImageUrl":"https://i.ibb.co/5TNnWM5/elemental-3058u.png","IsFeatured":false,"IsPublished":true,"Release":1.00,"Type":{"Id":21,"Name":"Infantry","Image":"Infantry.gif","SortOrder":3},"Role":{"Id":104,"Name":"None","Image":null,"SortOrder":0},"BFType":null,"BFSize":0,"BFMove":"0","BFTMM":0,"BFArmor":0,"BFStructure":0,"BFThreshold":0,"BFDamageShort":0,"BFDamageMedium":0,"BFDamageLong":0,"BFDamageExtreme":0,"BFOverheat":0,"BFPointValue":0,"BFAbilities":null,"Skill":0,"FormatedTonnage":"1"},{"Id":7921,"Name":"Elemental Battle Armor \u003cBase\u003e","GroupName":"","Class":"Elemental Battle Armor","Variant":"\u003cBase\u003e","Tonnage":1,"BattleValue":0,"Technology":{"Id":2,"Name":"Clan","Image":null,"SortOrder":0},"Cost":0,"Rules":"Standard","TROId":240,"TRO":"TR3058U","RSId":192,"RS":"None","EraIcon":"https://i.ibb.co/MB09bVm/era3-4-succession-wars.png","DateIntroduced":"2868","EraId":11,"EraStart":2781,"ImageUrl":"https://i.ibb.co/5TNnWM5/elemental-3058u.png","IsFeatured":false,"IsPublished":true,"Release":1.00,"Type":{"Id":21,"Name":"Infantry","Image":"Infantry.gif","SortOrder":3},"Role":{"Id":104,"Name":"None","Image":null,"SortOrder":0},"BFType":null,"BFSize":0,"BFMove":"0","BFTMM":0,"BFArmor":0,"BFStructure":0,"BFThreshold":0,"BFDamageShort":0,"BFDamageMedium":0,"BFDamageLong":0,"BFDamageExtreme":0,"BFOverheat":0,"BFPointValue":0,"BFAbilities":null,"Skill":0,"FormatedTonnage":"1"},{"Id":7671,"Name":"Water Elemental Mining Suit (Standard)","GroupName":"","Class":"Water Elemental Mining Suit","Variant":"(Standard)","Tonnage":1,"BattleValue":142,"Technology":{"Id":2,"Name":"Clan","Image":null,"SortOrder":0},"Cost":0,"Rules":"Experimental","TROId":445,"TRO":"TRGC","RSId":445,"RS":"TRGC","EraIcon":"https://i.ibb.co/MB09bVm/era3-4-succession-wars.png","DateIntroduced":"2842","EraId":11,"EraStart":2781,"ImageUrl":"https://i.ibb.co/pnJvQP6/water-elemental-trgc.png","IsFeatured":true,"IsPublished":true,"Release":1.00,"Type":{"Id":21,"Name":"Infantry","Image":"Infantry.gif","SortOrder":3},"Role":{"Id":104,"Name":"None","Image":null,"SortOrder":0},"BFType":null,"BFSize":0,"BFMove":"","BFTMM":0,"BFArmor":0,"BFStructure":0,"BFThreshold":0,"BFDamageShort":0,"BFDamageMedium":0,"BFDamageLong":0,"BFDamageExtreme":0,"BFOverheat":0,"BFPointValue":0,"BFAbilities":null,"Skill":0,"FormatedTonnage":"1"},{"Id":3677,"Name":"Afreet Medium Battle Armor (Hell\u0027s Horses)","GroupName":"","Class":"Afreet Medium Battle Armor","Variant":"(Hell\u0027s Horses)","Tonnage":1,"BattleValue":164,"Technology":{"Id":2,"Name":"Clan","Image":null,"SortOrder":0},"Cost":3640000,"Rules":"Standard","TROId":189,"TRO":"TR3075","RSId":396,"RS":"RS3075u-CE","EraIcon":"https://i.ibb.co/4jf2wfz/era7-jihad.png","DateIntroduced":"3072","EraId":14,"EraStart":3068,"ImageUrl":"https://i.ibb.co/MB2Sfzq/afreet-3075.png","IsFeatured":false,"IsPublished":true,"Release":1.30,"Type":{"Id":21,"Name":"Infantry","Image":"Infantry.gif","SortOrder":3},"Role":{"Id":105,"Name":"Scout","Image":null,"SortOrder":6},"BFType":"BA","BFSize":1,"BFMove":"8\"j","BFTMM":0,"BFArmor":1,"BFStructure":2,"BFThreshold":0,"BFDamageShort":2,"BFDamageMedium":0,"BFDamageLong":0,"BFDamageExtreme":0,"BFOverheat":0,"BFPointValue":15,"BFAbilities":"AM,CAR4,MEC","Skill":0,"FormatedTonnage":"1"},{"Id":5171,"Name":"Sylph Battle Armor (Enhanced)","GroupName":"","Class":"Sylph Battle Armor","Variant":"(Enhanced)","Tonnage":1,"BattleValue":164,"Technology":{"Id":2,"Name":"Clan","Image":null,"SortOrder":0},"Cost":3805400,"Rules":"Advanced","TROId":260,"TRO":"TRProto","RSId":428,"RS":"RSProto","EraIcon":"https://i.ibb.co/VtCdwyP/era8-10-republic-dark-age.png","DateIntroduced":"3085","EraId":15,"EraStart":3081,"ImageUrl":"https://i.ibb.co/Hg5F7ZH/sylph-proto.png","IsFeatured":true,"IsPublished":true,"Release":1.10,"Type":{"Id":21,"Name":"Infantry","Image":"Infantry.gif","SortOrder":3},"Role":{"Id":105,"Name":"Scout","Image":null,"SortOrder":6},"BFType":"BA","BFSize":1,"BFMove":"10\"f","BFTMM":0,"BFArmor":1,"BFStructure":2,"BFThreshold":0,"BFDamageShort":1,"BFDamageMedium":0,"BFDamageLong":0,"BFDamageExtreme":0,"BFOverheat":0,"BFPointValue":10,"BFAbilities":"AM,CAR4,MEC","Skill":0,"FormatedTonnage":"1"},{"Id":6234,"Name":"Buraq Fast Battle Armor (Hunter-Killer)","GroupName":"","Class":"Buraq Fast Battle Armor","Variant":"(Hunter-Killer)","Tonnage":1,"BattleValue":168,"Technology":{"Id":2,"Name":"Clan","Image":null,"SortOrder":0},"Cost":6112500,"Rules":"Standard","TROId":440,"TRO":"TR3145","RSId":439,"RS":"RS3145u","EraIcon":"https://i.ibb.co/VtCdwyP/era8-10-republic-dark-age.png","DateIntroduced":"3104","EraId":254,"EraStart":3101,"ImageUrl":"https://i.ibb.co/5WWdkDy/buraq-3145.png","IsFeatured":false,"IsPublished":true,"Release":1.00,"Type":{"Id":21,"Name":"Infantry","Image":"Infantry.gif","SortOrder":3},"Role":{"Id":105,"Name":"Scout","Image":null,"SortOrder":6},"BFType":"BA","BFSize":1,"BFMove":"14\"f","BFTMM":0,"BFArmor":1,"BFStructure":2,"BFThreshold":0,"BFDamageShort":2,"BFDamageMedium":0,"BFDamageLong":0,"BFDamageExtreme":0,"BFOverheat":0,"BFPointValue":20,"BFAbilities":"CAR4,RCN,SRCH","Skill":0,"FormatedTonnage":"1"},{"Id":16,"Name":"Afreet Medium Battle Armor (Interdictor)","GroupName":"","Class":"Afreet Medium Battle Armor","Variant":"(Interdictor)","Tonnage":1,"BattleValue":189,"Technology":{"Id":2,"Name":"Clan","Image":null,"SortOrder":0},"Cost":3890000,"Rules":"Standard","TROId":202,"TRO":"TR3085","RSId":257,"RS":"RS3085u-ONN","EraIcon":"https://i.ibb.co/4jf2wfz/era7-jihad.png","DateIntroduced":"3076","EraId":14,"EraStart":3068,"ImageUrl":"https://i.ibb.co/MB2Sfzq/afreet-3075.png","IsFeatured":false,"IsPublished":true,"Release":1.00,"Type":{"Id":21,"Name":"Infantry","Image":"Infantry.gif","SortOrder":3},"Role":{"Id":105,"Name":"Scout","Image":null,"SortOrder":6},"BFType":"BA","BFSize":1,"BFMove":"8\"j","BFTMM":0,"BFArmor":1,"BFStructure":2,"BFThreshold":0,"BFDamageShort":2,"BFDamageMedium":0,"BFDamageLong":0,"BFDamageExtreme":0,"BFOverheat":0,"BFPointValue":12,"BFAbilities":"AM,CAR4,FR,LECM,MEC","Skill":0,"FormatedTonnage":"1"},{"Id":6233,"Name":"Buraq Fast Battle Armor (Standard)","GroupName":"","Class":"Buraq Fast Battle Armor","Variant":"(Standard)","Tonnage":1,"BattleValue":199,"Technology":{"Id":2,"Name":"Clan","Image":null,"SortOrder":0},"Cost":5162500,"Rules":"Standard","TROId":440,"TRO":"TR3145","RSId":439,"RS":"RS3145u","EraIcon":"https://i.ibb.co/VtCdwyP/era8-10-republic-dark-age.png","DateIntroduced":"3104","EraId":254,"EraStart":3101,"ImageUrl":"https://i.ibb.co/5WWdkDy/buraq-3145.png","IsFeatured":true,"IsPublished":true,"Release":1.00,"Type":{"Id":21,"Name":"Infantry","Image":"Infantry.gif","SortOrder":3},"Role":{"Id":105,"Name":"Scout","Image":null,"SortOrder":6},"BFType":"BA","BFSize":1,"BFMove":"14\"f","BFTMM":0,"BFArmor":1,"BFStructure":2,"BFThreshold":0,"BFDamageShort":2,"BFDamageMedium":0,"BFDamageLong":0,"BFDamageExtreme":0,"BFOverheat":0,"BFPointValue":18,"BFAbilities":"CAR4,SRCH","Skill":0,"FormatedTonnage":"1"},{"Id":3351,"Name":"Undine Battle Armor (Standard)","GroupName":"","Class":"Undine Battle Armor","Variant":"(Standard)","Tonnage":1,"BattleValue":203,"Technology":{"Id":2,"Name":"Clan","Image":null,"SortOrder":0},"Cost":3560000,"Rules":"Standard","TROId":240,"TRO":"TR3058U","RSId":255,"RS":"RS3058Uu-C","EraIcon":"https://i.ibb.co/k6ySqKN/era5-clan-invasion.png","DateIntroduced":"3059","EraId":13,"EraStart":3050,"ImageUrl":"https://i.ibb.co/nggB1mn/undine-3058u.png","IsFeatured":true,"IsPublished":true,"Release":1.00,"Type":{"Id":21,"Name":"Infantry","Image":"Infantry.gif","SortOrder":3},"Role":{"Id":112,"Name":"Ambusher","Image":null,"SortOrder":1},"BFType":"BA","BFSize":1,"BFMove":"2\"f/6\"s","BFTMM":0,"BFArmor":1,"BFStructure":2,"BFThreshold":0,"BFDamageShort":1,"BFDamageMedium":0,"BFDamageLong":0,"BFDamageExtreme":0,"BFOverheat":0,"BFPointValue":11,"BFAbilities":"AM,CAR6,IF0*,MEC,SRCH,SUBS1","Skill":0,"FormatedTonnage":"1"},{"Id":953,"Name":"Elemental Battle Armor (Space) [Flamer]","GroupName":"","Class":"Elemental Battle Armor","Variant":"(Space) [Flamer]","Tonnage":1,"BattleValue":216,"Technology":{"Id":2,"Name":"Clan","Image":null,"SortOrder":0},"Cost":3905400,"Rules":"Standard","TROId":202,"TRO":"TR3085","RSId":257,"RS":"RS3085u-ONN","EraIcon":"https://i.ibb.co/MB09bVm/era3-4-succession-wars.png","DateIntroduced":"2903","EraId":255,"EraStart":2901,"ImageUrl":"https://i.ibb.co/5TNnWM5/elemental-3058u.png","IsFeatured":false,"IsPublished":true,"Release":1.00,"Type":{"Id":21,"Name":"Infantry","Image":"Infantry.gif","SortOrder":3},"Role":{"Id":112,"Name":"Ambusher","Image":null,"SortOrder":1},"BFType":"BA","BFSize":1,"BFMove":"6\"j","BFTMM":0,"BFArmor":1,"BFStructure":2,"BFThreshold":0,"BFDamageShort":1,"BFDamageMedium":0,"BFDamageLong":0,"BFDamageExtreme":0,"BFOverheat":0,"BFPointValue":10,"BFAbilities":"AM,CAR4,HT1/-/-,MEC,SOA","Skill":0,"FormatedTonnage":"1"},{"Id":954,"Name":"Elemental Battle Armor (Space) [MG]","GroupName":"","Class":"Elemental Battle Armor","Variant":"(Space) [MG]","Tonnage":1,"BattleValue":216,"Technology":{"Id":2,"Name":"Clan","Image":null,"SortOrder":0},"Cost":3892900,"Rules":"Standard","TROId":202,"TRO":"TR3085","RSId":257,"RS":"RS3085u-ONN","EraIcon":"https://i.ibb.co/MB09bVm/era3-4-succession-wars.png","DateIntroduced":"2903","EraId":255,"EraStart":2901,"ImageUrl":"https://i.ibb.co/5TNnWM5/elemental-3058u.png","IsFeatured":false,"IsPublished":true,"Release":1.00,"Type":{"Id":21,"Name":"Infantry","Image":"Infantry.gif","SortOrder":3},"Role":{"Id":112,"Name":"Ambusher","Image":null,"SortOrder":1},"BFType":"BA","BFSize":1,"BFMove":"6\"j","BFTMM":0,"BFArmor":1,"BFStructure":2,"BFThreshold":0,"BFDamageShort":1,"BFDamageMedium":0,"BFDamageLong":0,"BFDamageExtreme":0,"BFOverheat":0,"BFPointValue":10,"BFAbilities":"AM,CAR4,MEC,SOA","Skill":0,"FormatedTonnage":"1"},{"Id":3679,"Name":"Afreet Medium Battle Armor (Standard)","GroupName":"","Class":"Afreet Medium Battle Armor","Variant":"(Standard)","Tonnage":1,"BattleValue":217,"Technology":{"Id":2,"Name":"Clan","Image":null,"SortOrder":0},"Cost":4607500,"Rules":"Standard","TROId":189,"TRO":"TR3075","RSId":396,"RS":"RS3075u-CE","EraIcon":"https://i.ibb.co/QjhjKwr/era6-civil-war.png","DateIntroduced":"3067","EraId":247,"EraStart":3062,"ImageUrl":"https://i.ibb.co/MB2Sfzq/afreet-3075.png","IsFeatured":true,"IsPublished":true,"Release":1.30,"Type":{"Id":21,"Name":"Infantry","Image":"Infantry.gif","SortOrder":3},"Role":{"Id":105,"Name":"Scout","Image":null,"SortOrder":6},"BFType":"BA","BFSize":1,"BFMove":"8\"j","BFTMM":0,"BFArmor":1,"BFStructure":2,"BFThreshold":0,"BFDamageShort":1,"BFDamageMedium":1,"BFDamageLong":0,"BFDamageExtreme":0,"BFOverheat":0,"BFPointValue":17,"BFAbilities":"AM,CAR4,MEC,RCN","Skill":0,"FormatedTonnage":"1"},{"Id":952,"Name":"Elemental Battle Armor (Headhunter)","GroupName":"","Class":"Elemental Battle Armor","Variant":"(Headhunter)","Tonnage":1,"BattleValue":223,"Technology":{"Id":2,"Name":"Clan","Image":null,"SortOrder":0},"Cost":4530400,"Rules":"Standard","TROId":240,"TRO":"TR3058U","RSId":255,"RS":"RS3058Uu-C","EraIcon":"https://i.ibb.co/k6ySqKN/era5-clan-invasion.png","DateIntroduced":"3050","EraId":13,"EraStart":3050,"ImageUrl":"https://i.ibb.co/5TNnWM5/elemental-3058u.png","IsFeatured":false,"IsPublished":true,"Release":1.00,"Type":{"Id":21,"Name":"Infantry","Image":"Infantry.gif","SortOrder":3},"Role":{"Id":112,"Name":"Ambusher","Image":null,"SortOrder":1},"BFType":"BA","BFSize":1,"BFMove":"6\"j","BFTMM":0,"BFArmor":1,"BFStructure":2,"BFThreshold":0,"BFDamageShort":1,"BFDamageMedium":0,"BFDamageLong":0,"BFDamageExtreme":0,"BFOverheat":0,"BFPointValue":12,"BFAbilities":"AM,CAR4,MEC,RCN,RSD1","Skill":0,"FormatedTonnage":"1"},{"Id":3957,"Name":"Clan Medium Battle Armor (Standard) \"Rabid\"","GroupName":"","Class":"Clan Medium Battle Armor","Variant":"(Standard) \"Rabid\"","Tonnage":1,"BattleValue":241,"Technology":{"Id":2,"Name":"Clan","Image":null,"SortOrder":0},"Cost":0,"Rules":"Standard","TROId":189,"TRO":"TR3075","RSId":396,"RS":"RS3075u-CE","EraIcon":"https://i.ibb.co/QjhjKwr/era6-civil-war.png","DateIntroduced":"3067","EraId":247,"EraStart":3062,"ImageUrl":"https://i.ibb.co/vwmb19d/clan-medium-3075.png","IsFeatured":true,"IsPublished":true,"Release":1.30,"Type":{"Id":21,"Name":"Infantry","Image":"Infantry.gif","SortOrder":3},"Role":{"Id":105,"Name":"Scout","Image":null,"SortOrder":6},"BFType":"BA","BFSize":1,"BFMove":"8\"j","BFTMM":0,"BFArmor":1,"BFStructure":2,"BFThreshold":0,"BFDamageShort":1,"BFDamageMedium":0,"BFDamageLong":0,"BFDamageExtreme":0,"BFOverheat":0,"BFPointValue":15,"BFAbilities":"AM,CAR4,HT1/-/-,MEC,SRCH","Skill":0,"FormatedTonnage":"1"},{"Id":3955,"Name":"Clan Medium Battle Armor (Laser) \"Volk\"","GroupName":"","Class":"Clan Medium Battle Armor","Variant":"(Laser) \"Volk\"","Tonnage":1,"BattleValue":250,"Technology":{"Id":2,"Name":"Clan","Image":null,"SortOrder":0},"Cost":0,"Rules":"Standard","TROId":189,"TRO":"TR3075","RSId":396,"RS":"RS3075u-CE","EraIcon":"https://i.ibb.co/4jf2wfz/era7-jihad.png","DateIntroduced":"3071","EraId":14,"EraStart":3068,"ImageUrl":"https://i.ibb.co/vwmb19d/clan-medium-3075.png","IsFeatured":false,"IsPublished":true,"Release":1.30,"Type":{"Id":21,"Name":"Infantry","Image":"Infantry.gif","SortOrder":3},"Role":{"Id":105,"Name":"Scout","Image":null,"SortOrder":6},"BFType":"BA","BFSize":1,"BFMove":"8\"j","BFTMM":0,"BFArmor":1,"BFStructure":2,"BFThreshold":0,"BFDamageShort":1,"BFDamageMedium":0,"BFDamageLong":0,"BFDamageExtreme":0,"BFOverheat":0,"BFPointValue":14,"BFAbilities":"AM,CAR4,MEC,SRCH","Skill":0,"FormatedTonnage":"1"},{"Id":3956,"Name":"Clan Medium Battle Armor (Naval) \"Bär\"","GroupName":"","Class":"Clan Medium Battle Armor","Variant":"(Naval) \"Bär\"","Tonnage":1,"BattleValue":269,"Technology":{"Id":2,"Name":"Clan","Image":null,"SortOrder":0},"Cost":0,"Rules":"Standard","TROId":189,"TRO":"TR3075","RSId":396,"RS":"RS3075u-CE","EraIcon":"https://i.ibb.co/4jf2wfz/era7-jihad.png","DateIntroduced":"3070","EraId":14,"EraStart":3068,"ImageUrl":"https://i.ibb.co/vwmb19d/clan-medium-3075.png","IsFeatured":false,"IsPublished":true,"Release":1.30,"Type":{"Id":21,"Name":"Infantry","Image":"Infantry.gif","SortOrder":3},"Role":{"Id":105,"Name":"Scout","Image":null,"SortOrder":6},"BFType":"BA","BFSize":1,"BFMove":"8\"j","BFTMM":0,"BFArmor":1,"BFStructure":2,"BFThreshold":0,"BFDamageShort":2,"BFDamageMedium":0,"BFDamageLong":0,"BFDamageExtreme":0,"BFOverheat":0,"BFPointValue":11,"BFAbilities":"AM,CAR4,MEC,SRCH","Skill":0,"FormatedTonnage":"1"},{"Id":955,"Name":"Elemental Battle Armor (Space) [MicroPL]","GroupName":"","Class":"Elemental Battle Armor","Variant":"(Space) [MicroPL]","Tonnage":1,"BattleValue":272,"Technology":{"Id":2,"Name":"Clan","Image":null,"SortOrder":0},"Cost":3930400,"Rules":"Standard","TROId":202,"TRO":"TR3085","RSId":257,"RS":"RS3085u-ONN","EraIcon":"https://i.ibb.co/QjhjKwr/era6-civil-war.png","DateIntroduced":"3066","EraId":247,"EraStart":3062,"ImageUrl":"https://i.ibb.co/5TNnWM5/elemental-3058u.png","IsFeatured":false,"IsPublished":true,"Release":1.00,"Type":{"Id":21,"Name":"Infantry","Image":"Infantry.gif","SortOrder":3},"Role":{"Id":112,"Name":"Ambusher","Image":null,"SortOrder":1},"BFType":"BA","BFSize":1,"BFMove":"6\"j","BFTMM":0,"BFArmor":1,"BFStructure":2,"BFThreshold":0,"BFDamageShort":2,"BFDamageMedium":0,"BFDamageLong":0,"BFDamageExtreme":0,"BFOverheat":0,"BFPointValue":10,"BFAbilities":"AM,CAR4,MEC,SOA","Skill":0,"FormatedTonnage":"1"},{"Id":635,"Name":"Clan Medium Battle Armor \"Rache\"","GroupName":"","Class":"Clan Medium Battle Armor","Variant":"\"Rache\"","Tonnage":1,"BattleValue":276,"Technology":{"Id":2,"Name":"Clan","Image":null,"SortOrder":0},"Cost":0,"Rules":"Standard","TROId":202,"TRO":"TR3085","RSId":257,"RS":"RS3085u-ONN","EraIcon":"https://i.ibb.co/4jf2wfz/era7-jihad.png","DateIntroduced":"3077","EraId":14,"EraStart":3068,"ImageUrl":"https://i.ibb.co/vwmb19d/clan-medium-3075.png","IsFeatured":false,"IsPublished":true,"Release":1.00,"Type":{"Id":21,"Name":"Infantry","Image":"Infantry.gif","SortOrder":3},"Role":{"Id":105,"Name":"Scout","Image":null,"SortOrder":6},"BFType":"BA","BFSize":1,"BFMove":"8\"j","BFTMM":0,"BFArmor":1,"BFStructure":2,"BFThreshold":0,"BFDamageShort":1,"BFDamageMedium":0,"BFDamageLong":0,"BFDamageExtreme":0,"BFOverheat":0,"BFPointValue":14,"BFAbilities":"AM,CAR4,MEC,SRCH","Skill":0,"FormatedTonnage":"1"},{"Id":2789,"Name":"Salamander Battle Armor (Standard)","GroupName":"","Class":"Salamander Battle Armor","Variant":"(Standard)","Tonnage":1,"BattleValue":276,"Technology":{"Id":2,"Name":"Clan","Image":null,"SortOrder":0},"Cost":3397500,"Rules":"Standard","TROId":240,"TRO":"TR3058U","RSId":255,"RS":"RS3058Uu-C","EraIcon":"https://i.ibb.co/k6ySqKN/era5-clan-invasion.png","DateIntroduced":"3058","EraId":13,"EraStart":3050,"ImageUrl":"https://i.ibb.co/475v1xK/salamander-3058u.png","IsFeatured":true,"IsPublished":true,"Release":1.00,"Type":{"Id":21,"Name":"Infantry","Image":"Infantry.gif","SortOrder":3},"Role":{"Id":112,"Name":"Ambusher","Image":null,"SortOrder":1},"BFType":"BA","BFSize":1,"BFMove":"6\"j","BFTMM":0,"BFArmor":1,"BFStructure":2,"BFThreshold":0,"BFDamageShort":2,"BFDamageMedium":0,"BFDamageLong":0,"BFDamageExtreme":0,"BFOverheat":0,"BFPointValue":17,"BFAbilities":"AM,CAR4,FR,HT2/-/-,MEC","Skill":0,"FormatedTonnage":"1"},{"Id":6237,"Name":"Wraith Battle Armor (Anti-Infantry)","GroupName":"","Class":"Wraith Battle Armor","Variant":"(Anti-Infantry)","Tonnage":1,"BattleValue":290,"Technology":{"Id":2,"Name":"Clan","Image":null,"SortOrder":0},"Cost":4517500,"Rules":"Standard","TROId":440,"TRO":"TR3145","RSId":439,"RS":"RS3145u","EraIcon":"https://i.ibb.co/VtCdwyP/era8-10-republic-dark-age.png","DateIntroduced":"3116","EraId":254,"EraStart":3101,"ImageUrl":"https://i.ibb.co/jbrbCC6/wraith-3145.png","IsFeatured":false,"IsPublished":true,"Release":1.00,"Type":{"Id":21,"Name":"Infantry","Image":"Infantry.gif","SortOrder":3},"Role":{"Id":112,"Name":"Ambusher","Image":null,"SortOrder":1},"BFType":"BA","BFSize":1,"BFMove":"6\"j","BFTMM":0,"BFArmor":1,"BFStructure":2,"BFThreshold":0,"BFDamageShort":1,"BFDamageMedium":0,"BFDamageLong":0,"BFDamageExtreme":0,"BFOverheat":0,"BFPointValue":12,"BFAbilities":"AM,CAR4,MEC,RCA,RCN","Skill":0,"FormatedTonnage":"1"},{"Id":6236,"Name":"Wraith Battle Armor (Standard)","GroupName":"","Class":"Wraith Battle Armor","Variant":"(Standard)","Tonnage":1,"BattleValue":291,"Technology":{"Id":2,"Name":"Clan","Image":null,"SortOrder":0},"Cost":3662500,"Rules":"Standard","TROId":440,"TRO":"TR3145","RSId":439,"RS":"RS3145u","EraIcon":"https://i.ibb.co/VtCdwyP/era8-10-republic-dark-age.png","DateIntroduced":"3116","EraId":254,"EraStart":3101,"ImageUrl":"https://i.ibb.co/jbrbCC6/wraith-3145.png","IsFeatured":true,"IsPublished":true,"Release":1.00,"Type":{"Id":21,"Name":"Infantry","Image":"Infantry.gif","SortOrder":3},"Role":{"Id":112,"Name":"Ambusher","Image":null,"SortOrder":1},"BFType":"BA","BFSize":1,"BFMove":"6\"j","BFTMM":0,"BFArmor":1,"BFStructure":2,"BFThreshold":0,"BFDamageShort":2,"BFDamageMedium":0,"BFDamageLong":0,"BFDamageExtreme":0,"BFOverheat":0,"BFPointValue":11,"BFAbilities":"AM,CAR4,MEC,STL","Skill":0,"FormatedTonnage":"1"},{"Id":2788,"Name":"Salamander Battle Armor (Laser)","GroupName":"","Class":"Salamander Battle Armor","Variant":"(Laser)","Tonnage":1,"BattleValue":292,"Technology":{"Id":2,"Name":"Clan","Image":null,"SortOrder":0},"Cost":3410000,"Rules":"Standard","TROId":240,"TRO":"TR3058U","RSId":255,"RS":"RS3058Uu-C","EraIcon":"https://i.ibb.co/QjhjKwr/era6-civil-war.png","DateIntroduced":"3064","EraId":247,"EraStart":3062,"ImageUrl":"https://i.ibb.co/475v1xK/salamander-3058u.png","IsFeatured":false,"IsPublished":true,"Release":1.00,"Type":{"Id":21,"Name":"Infantry","Image":"Infantry.gif","SortOrder":3},"Role":{"Id":112,"Name":"Ambusher","Image":null,"SortOrder":1},"BFType":"BA","BFSize":1,"BFMove":"6\"j","BFTMM":0,"BFArmor":1,"BFStructure":2,"BFThreshold":0,"BFDamageShort":2,"BFDamageMedium":0,"BFDamageLong":0,"BFDamageExtreme":0,"BFOverheat":0,"BFPointValue":16,"BFAbilities":"AM,CAR4,FR,HT1/-/-,MEC","Skill":0,"FormatedTonnage":"1"},{"Id":2787,"Name":"Salamander Battle Armor (Anti-Infantry)","GroupName":"","Class":"Salamander Battle Armor","Variant":"(Anti-Infantry)","Tonnage":1,"BattleValue":293,"Technology":{"Id":2,"Name":"Clan","Image":null,"SortOrder":0},"Cost":3397500,"Rules":"Standard","TROId":240,"TRO":"TR3058U","RSId":255,"RS":"RS3058Uu-C","EraIcon":"https://i.ibb.co/4jf2wfz/era7-jihad.png","DateIntroduced":"3070","EraId":14,"EraStart":3068,"ImageUrl":"https://i.ibb.co/475v1xK/salamander-3058u.png","IsFeatured":false,"IsPublished":true,"Release":1.00,"Type":{"Id":21,"Name":"Infantry","Image":"Infantry.gif","SortOrder":3},"Role":{"Id":112,"Name":"Ambusher","Image":null,"SortOrder":1},"BFType":"BA","BFSize":1,"BFMove":"6\"j","BFTMM":0,"BFArmor":1,"BFStructure":2,"BFThreshold":0,"BFDamageShort":3,"BFDamageMedium":0,"BFDamageLong":0,"BFDamageExtreme":0,"BFOverheat":0,"BFPointValue":16,"BFAbilities":"AM,CAR4,FR,MEC","Skill":0,"FormatedTonnage":"1"},{"Id":950,"Name":"Elemental Battle Armor (Fire) [Flamer]","GroupName":"","Class":"Elemental Battle Armor","Variant":"(Fire) [Flamer]","Tonnage":1,"BattleValue":299,"Technology":{"Id":2,"Name":"Clan","Image":null,"SortOrder":0},"Cost":3590000,"Rules":"Standard","TROId":202,"TRO":"TR3085","RSId":257,"RS":"RS3085u-ONN","EraIcon":"https://i.ibb.co/4jf2wfz/era7-jihad.png","DateIntroduced":"3069","EraId":14,"EraStart":3068,"ImageUrl":"https://i.ibb.co/5TNnWM5/elemental-3058u.png","IsFeatured":false,"IsPublished":true,"Release":1.00,"Type":{"Id":21,"Name":"Infantry","Image":"Infantry.gif","SortOrder":3},"Role":{"Id":112,"Name":"Ambusher","Image":null,"SortOrder":1},"BFType":"BA","BFSize":1,"BFMove":"6\"j","BFTMM":0,"BFArmor":1,"BFStructure":2,"BFThreshold":0,"BFDamageShort":1,"BFDamageMedium":0,"BFDamageLong":0,"BFDamageExtreme":0,"BFOverheat":0,"BFPointValue":15,"BFAbilities":"AM,CAR4,FR,HT1/-/-,MEC","Skill":0,"FormatedTonnage":"1"},{"Id":958,"Name":"Elemental Battle Armor [Flamer]","GroupName":"","Class":"Elemental Battle Armor","Variant":"[Flamer]","Tonnage":1,"BattleValue":300,"Technology":{"Id":2,"Name":"Clan","Image":null,"SortOrder":0},"Cost":3480400,"Rules":"Standard","TROId":240,"TRO":"TR3058U","RSId":255,"RS":"RS3058Uu-C","EraIcon":"https://i.ibb.co/MB09bVm/era3-4-succession-wars.png","DateIntroduced":"2868","EraId":11,"EraStart":2781,"ImageUrl":"https://i.ibb.co/5TNnWM5/elemental-3058u.png","IsFeatured":false,"IsPublished":true,"Release":1.00,"Type":{"Id":21,"Name":"Infantry","Image":"Infantry.gif","SortOrder":3},"Role":{"Id":112,"Name":"Ambusher","Image":null,"SortOrder":1},"BFType":"BA","BFSize":1,"BFMove":"6\"j","BFTMM":0,"BFArmor":1,"BFStructure":2,"BFThreshold":0,"BFDamageShort":2,"BFDamageMedium":1,"BFDamageLong":0,"BFDamageExtreme":0,"BFOverheat":0,"BFPointValue":17,"BFAbilities":"AM,CAR4,HT1/-/-,MEC","Skill":0,"FormatedTonnage":"1"},{"Id":961,"Name":"Elemental Battle Armor [MG]","GroupName":"","Class":"Elemental Battle Armor","Variant":"[MG]","Tonnage":1,"BattleValue":300,"Technology":{"Id":2,"Name":"Clan","Image":null,"SortOrder":0},"Cost":3467900,"Rules":"Standard","TROId":240,"TRO":"TR3058U","RSId":255,"RS":"RS3058Uu-C","EraIcon":"https://i.ibb.co/MB09bVm/era3-4-succession-wars.png","DateIntroduced":"2868","EraId":11,"EraStart":2781,"ImageUrl":"https://i.ibb.co/5TNnWM5/elemental-3058u.png","IsFeatured":false,"IsPublished":true,"Release":1.00,"Type":{"Id":21,"Name":"Infantry","Image":"Infantry.gif","SortOrder":3},"Role":{"Id":112,"Name":"Ambusher","Image":null,"SortOrder":1},"BFType":"BA","BFSize":1,"BFMove":"6\"j","BFTMM":0,"BFArmor":1,"BFStructure":2,"BFThreshold":0,"BFDamageShort":2,"BFDamageMedium":1,"BFDamageLong":0,"BFDamageExtreme":0,"BFOverheat":0,"BFPointValue":16,"BFAbilities":"AM,CAR4,MEC","Skill":0,"FormatedTonnage":"1"},{"Id":959,"Name":"Elemental Battle Armor [HMG]","GroupName":"","Class":"Elemental Battle Armor","Variant":"[HMG]","Tonnage":1,"BattleValue":308,"Technology":{"Id":2,"Name":"Clan","Image":null,"SortOrder":0},"Cost":3480400,"Rules":"Standard","TROId":240,"TRO":"TR3058U","RSId":255,"RS":"RS3058Uu-C","EraIcon":"https://i.ibb.co/k6ySqKN/era5-clan-invasion.png","DateIntroduced":"3059","EraId":13,"EraStart":3050,"ImageUrl":"https://i.ibb.co/5TNnWM5/elemental-3058u.png","IsFeatured":false,"IsPublished":true,"Release":1.00,"Type":{"Id":21,"Name":"Infantry","Image":"Infantry.gif","SortOrder":3},"Role":{"Id":112,"Name":"Ambusher","Image":null,"SortOrder":1},"BFType":"BA","BFSize":1,"BFMove":"6\"j","BFTMM":0,"BFArmor":1,"BFStructure":2,"BFThreshold":0,"BFDamageShort":2,"BFDamageMedium":1,"BFDamageLong":0,"BFDamageExtreme":0,"BFOverheat":0,"BFPointValue":16,"BFAbilities":"AM,CAR4,MEC","Skill":0,"FormatedTonnage":"1"},{"Id":957,"Name":"Elemental Battle Armor [ERMicroL]","GroupName":"","Class":"Elemental Battle Armor","Variant":"[ERMicroL]","Tonnage":1,"BattleValue":316,"Technology":{"Id":2,"Name":"Clan","Image":null,"SortOrder":0},"Cost":0,"Rules":"Standard","TROId":240,"TRO":"TR3058U","RSId":255,"RS":"RS3058Uu-C","EraIcon":"https://i.ibb.co/k6ySqKN/era5-clan-invasion.png","DateIntroduced":"3060","EraId":13,"EraStart":3050,"ImageUrl":"https://i.ibb.co/5TNnWM5/elemental-3058u.png","IsFeatured":false,"IsPublished":true,"Release":1.00,"Type":{"Id":21,"Name":"Infantry","Image":"Infantry.gif","SortOrder":3},"Role":{"Id":112,"Name":"Ambusher","Image":null,"SortOrder":1},"BFType":"BA","BFSize":1,"BFMove":"6\"j","BFTMM":0,"BFArmor":1,"BFStructure":2,"BFThreshold":0,"BFDamageShort":2,"BFDamageMedium":1,"BFDamageLong":0,"BFDamageExtreme":0,"BFOverheat":0,"BFPointValue":16,"BFAbilities":"AM,CAR4,MEC","Skill":0,"FormatedTonnage":"1"},{"Id":3678,"Name":"Afreet Medium Battle Armor (Jade Falcon)","GroupName":"","Class":"Afreet Medium Battle Armor","Variant":"(Jade Falcon)","Tonnage":1,"BattleValue":326,"Technology":{"Id":2,"Name":"Clan","Image":null,"SortOrder":0},"Cost":3652500,"Rules":"Standard","TROId":189,"TRO":"TR3075","RSId":396,"RS":"RS3075u-CE","EraIcon":"https://i.ibb.co/4jf2wfz/era7-jihad.png","DateIntroduced":"3072","EraId":14,"EraStart":3068,"ImageUrl":"https://i.ibb.co/MB2Sfzq/afreet-3075.png","IsFeatured":false,"IsPublished":true,"Release":1.30,"Type":{"Id":21,"Name":"Infantry","Image":"Infantry.gif","SortOrder":3},"Role":{"Id":105,"Name":"Scout","Image":null,"SortOrder":6},"BFType":"BA","BFSize":1,"BFMove":"8\"j","BFTMM":0,"BFArmor":1,"BFStructure":2,"BFThreshold":0,"BFDamageShort":2,"BFDamageMedium":2,"BFDamageLong":0,"BFDamageExtreme":0,"BFOverheat":0,"BFPointValue":19,"BFAbilities":"AM,CAR4,FR,MEC","Skill":0,"FormatedTonnage":"1"},{"Id":6235,"Name":"Buraq Fast Battle Armor (Support)","GroupName":"","Class":"Buraq Fast Battle Armor","Variant":"(Support)","Tonnage":1,"BattleValue":330,"Technology":{"Id":2,"Name":"Clan","Image":null,"SortOrder":0},"Cost":5460000,"Rules":"Standard","TROId":440,"TRO":"TR3145","RSId":439,"RS":"RS3145u","EraIcon":"https://i.ibb.co/VtCdwyP/era8-10-republic-dark-age.png","DateIntroduced":"3104","EraId":254,"EraStart":3101,"ImageUrl":"https://i.ibb.co/5WWdkDy/buraq-3145.png","IsFeatured":false,"IsPublished":true,"Release":1.00,"Type":{"Id":21,"Name":"Infantry","Image":"Infantry.gif","SortOrder":3},"Role":{"Id":105,"Name":"Scout","Image":null,"SortOrder":6},"BFType":"BA","BFSize":1,"BFMove":"14\"f","BFTMM":0,"BFArmor":1,"BFStructure":2,"BFThreshold":0,"BFDamageShort":2,"BFDamageMedium":2,"BFDamageLong":0,"BFDamageExtreme":0,"BFOverheat":0,"BFPointValue":24,"BFAbilities":"CAR4,LTAG","Skill":0,"FormatedTonnage":"1"},{"Id":960,"Name":"Elemental Battle Armor [Laser]","GroupName":"","Class":"Elemental Battle Armor","Variant":"[Laser]","Tonnage":1,"BattleValue":332,"Technology":{"Id":2,"Name":"Clan","Image":null,"SortOrder":0},"Cost":3499150,"Rules":"Standard","TROId":240,"TRO":"TR3058U","RSId":255,"RS":"RS3058Uu-C","EraIcon":"https://i.ibb.co/MB09bVm/era3-4-succession-wars.png","DateIntroduced":"2868","EraId":11,"EraStart":2781,"ImageUrl":"https://i.ibb.co/5TNnWM5/elemental-3058u.png","IsFeatured":false,"IsPublished":true,"Release":1.00,"Type":{"Id":21,"Name":"Infantry","Image":"Infantry.gif","SortOrder":3},"Role":{"Id":112,"Name":"Ambusher","Image":null,"SortOrder":1},"BFType":"BA","BFSize":1,"BFMove":"6\"j","BFTMM":0,"BFArmor":1,"BFStructure":2,"BFThreshold":0,"BFDamageShort":2,"BFDamageMedium":1,"BFDamageLong":0,"BFDamageExtreme":0,"BFOverheat":0,"BFPointValue":16,"BFAbilities":"AM,CAR4,MEC","Skill":0,"FormatedTonnage":"1"},{"Id":3352,"Name":"Undine Battle Armor (Upgrade)","GroupName":"","Class":"Undine Battle Armor","Variant":"(Upgrade)","Tonnage":1,"BattleValue":336,"Technology":{"Id":2,"Name":"Clan","Image":null,"SortOrder":0},"Cost":3422500,"Rules":"Standard","TROId":240,"TRO":"TR3058U","RSId":255,"RS":"RS3058Uu-C","EraIcon":"https://i.ibb.co/4jf2wfz/era7-jihad.png","DateIntroduced":"3069","EraId":14,"EraStart":3068,"ImageUrl":"https://i.ibb.co/nggB1mn/undine-3058u.png","IsFeatured":false,"IsPublished":true,"Release":1.00,"Type":{"Id":21,"Name":"Infantry","Image":"Infantry.gif","SortOrder":3},"Role":{"Id":110,"Name":"Missile Boat","Image":null,"SortOrder":4},"BFType":"BA","BFSize":1,"BFMove":"6\"j","BFTMM":0,"BFArmor":1,"BFStructure":2,"BFThreshold":0,"BFDamageShort":2,"BFDamageMedium":1,"BFDamageLong":1,"BFDamageExtreme":0,"BFOverheat":0,"BFPointValue":18,"BFAbilities":"AM,CAR4,IF1,MEC","Skill":0,"FormatedTonnage":"1"},{"Id":4123,"Name":"Elemental II Battle Armor (Standard)","GroupName":"","Class":"Elemental II Battle Armor","Variant":"(Standard)","Tonnage":1,"BattleValue":354,"Technology":{"Id":2,"Name":"Clan","Image":null,"SortOrder":0},"Cost":3842900,"Rules":"Advanced","TROId":260,"TRO":"TRProto","RSId":428,"RS":"RSProto","EraIcon":"https://i.ibb.co/VtCdwyP/era8-10-republic-dark-age.png","DateIntroduced":"3084","EraId":15,"EraStart":3081,"ImageUrl":"https://i.ibb.co/G00w9Zh/elemental-ii-proto.png","IsFeatured":true,"IsPublished":true,"Release":1.10,"Type":{"Id":21,"Name":"Infantry","Image":"Infantry.gif","SortOrder":3},"Role":{"Id":105,"Name":"Scout","Image":null,"SortOrder":6},"BFType":"BA","BFSize":1,"BFMove":"8\"f","BFTMM":0,"BFArmor":1,"BFStructure":2,"BFThreshold":0,"BFDamageShort":2,"BFDamageMedium":2,"BFDamageLong":0,"BFDamageExtreme":0,"BFOverheat":0,"BFPointValue":14,"BFAbilities":"AM,CAR4,MEC","Skill":0,"FormatedTonnage":"1"},{"Id":951,"Name":"Elemental Battle Armor (Fire) [MicroPL]","GroupName":"","Class":"Elemental Battle Armor","Variant":"(Fire) [MicroPL]","Tonnage":1,"BattleValue":355,"Technology":{"Id":2,"Name":"Clan","Image":null,"SortOrder":0},"Cost":3615000,"Rules":"Standard","TROId":202,"TRO":"TR3085","RSId":257,"RS":"RS3085u-ONN","EraIcon":"https://i.ibb.co/4jf2wfz/era7-jihad.png","DateIntroduced":"3069","EraId":14,"EraStart":3068,"ImageUrl":"https://i.ibb.co/5TNnWM5/elemental-3058u.png","IsFeatured":false,"IsPublished":true,"Release":1.00,"Type":{"Id":21,"Name":"Infantry","Image":"Infantry.gif","SortOrder":3},"Role":{"Id":112,"Name":"Ambusher","Image":null,"SortOrder":1},"BFType":"BA","BFSize":1,"BFMove":"6\"j","BFTMM":0,"BFArmor":1,"BFStructure":2,"BFThreshold":0,"BFDamageShort":2,"BFDamageMedium":0,"BFDamageLong":0,"BFDamageExtreme":0,"BFOverheat":0,"BFPointValue":15,"BFAbilities":"AM,CAR4,FR,MEC","Skill":0,"FormatedTonnage":"1"},{"Id":962,"Name":"Elemental Battle Armor [MicroPL]","GroupName":"","Class":"Elemental Battle Armor","Variant":"[MicroPL]","Tonnage":1,"BattleValue":356,"Technology":{"Id":2,"Name":"Clan","Image":null,"SortOrder":0},"Cost":3505400,"Rules":"Standard","TROId":240,"TRO":"TR3058U","RSId":255,"RS":"RS3058Uu-C","EraIcon":"https://i.ibb.co/k6ySqKN/era5-clan-invasion.png","DateIntroduced":"3060","EraId":13,"EraStart":3050,"ImageUrl":"https://i.ibb.co/5TNnWM5/elemental-3058u.png","IsFeatured":false,"IsPublished":true,"Release":1.00,"Type":{"Id":21,"Name":"Infantry","Image":"Infantry.gif","SortOrder":3},"Role":{"Id":112,"Name":"Ambusher","Image":null,"SortOrder":1},"BFType":"BA","BFSize":1,"BFMove":"6\"j","BFTMM":0,"BFArmor":1,"BFStructure":2,"BFThreshold":0,"BFDamageShort":2,"BFDamageMedium":1,"BFDamageLong":0,"BFDamageExtreme":0,"BFOverheat":0,"BFPointValue":16,"BFAbilities":"AM,CAR4,MEC","Skill":0,"FormatedTonnage":"1"},{"Id":949,"Name":"Elemental Battle Armor (Fire) [AP Gauss]","GroupName":"","Class":"Elemental Battle Armor","Variant":"(Fire) [AP Gauss]","Tonnage":1,"BattleValue":428,"Technology":{"Id":2,"Name":"Clan","Image":null,"SortOrder":0},"Cost":3602500,"Rules":"Standard","TROId":202,"TRO":"TR3085","RSId":257,"RS":"RS3085u-ONN","EraIcon":"https://i.ibb.co/4jf2wfz/era7-jihad.png","DateIntroduced":"3069","EraId":14,"EraStart":3068,"ImageUrl":"https://i.ibb.co/5TNnWM5/elemental-3058u.png","IsFeatured":false,"IsPublished":true,"Release":1.00,"Type":{"Id":21,"Name":"Infantry","Image":"Infantry.gif","SortOrder":3},"Role":{"Id":112,"Name":"Ambusher","Image":null,"SortOrder":1},"BFType":"BA","BFSize":1,"BFMove":"6\"j","BFTMM":0,"BFArmor":1,"BFStructure":2,"BFThreshold":0,"BFDamageShort":2,"BFDamageMedium":2,"BFDamageLong":0,"BFDamageExtreme":0,"BFOverheat":0,"BFPointValue":18,"BFAbilities":"AM,CAR4,FR,MEC","Skill":0,"FormatedTonnage":"1"},{"Id":956,"Name":"Elemental Battle Armor [AP Gauss]","GroupName":"","Class":"Elemental Battle Armor","Variant":"[AP Gauss]","Tonnage":1,"BattleValue":428,"Technology":{"Id":2,"Name":"Clan","Image":null,"SortOrder":0},"Cost":3492900,"Rules":"Standard","TROId":240,"TRO":"TR3058U","RSId":255,"RS":"RS3058Uu-C","EraIcon":"https://i.ibb.co/4jf2wfz/era7-jihad.png","DateIntroduced":"3069","EraId":14,"EraStart":3068,"ImageUrl":"https://i.ibb.co/5TNnWM5/elemental-3058u.png","IsFeatured":false,"IsPublished":true,"Release":1.00,"Type":{"Id":21,"Name":"Infantry","Image":"Infantry.gif","SortOrder":3},"Role":{"Id":112,"Name":"Ambusher","Image":null,"SortOrder":1},"BFType":"BA","BFSize":1,"BFMove":"6\"j","BFTMM":0,"BFArmor":1,"BFStructure":2,"BFThreshold":0,"BFDamageShort":2,"BFDamageMedium":2,"BFDamageLong":0,"BFDamageExtreme":0,"BFOverheat":0,"BFPointValue":18,"BFAbilities":"AM,CAR4,MEC","Skill":0,"FormatedTonnage":"1"},{"Id":4221,"Name":"Gnome Battle Armor (Upgrade) \u003cBase\u003e","GroupName":"","Class":"Gnome Battle Armor","Variant":"(Upgrade) \u003cBase\u003e","Tonnage":1.5,"BattleValue":0,"Technology":{"Id":2,"Name":"Clan","Image":null,"SortOrder":0},"Cost":0,"Rules":"Standard","TROId":240,"TRO":"TR3058U","RSId":192,"RS":"None","EraIcon":"https://i.ibb.co/4jf2wfz/era7-jihad.png","DateIntroduced":"3069","EraId":14,"EraStart":3068,"ImageUrl":"https://i.ibb.co/YW015j5/gnome-3058u.png","IsFeatured":false,"IsPublished":true,"Release":1.10,"Type":{"Id":21,"Name":"Infantry","Image":"Infantry.gif","SortOrder":3},"Role":{"Id":104,"Name":"None","Image":null,"SortOrder":0},"BFType":null,"BFSize":0,"BFMove":"","BFTMM":0,"BFArmor":0,"BFStructure":0,"BFThreshold":0,"BFDamageShort":0,"BFDamageMedium":0,"BFDamageLong":0,"BFDamageExtreme":0,"BFOverheat":0,"BFPointValue":0,"BFAbilities":null,"Skill":0,"FormatedTonnage":"1.5"},{"Id":6238,"Name":"Black Wolf Battle Armor \u003cBase\u003e","GroupName":"","Class":"Black Wolf Battle Armor","Variant":"\u003cBase\u003e","Tonnage":1.5,"BattleValue":0,"Technology":{"Id":2,"Name":"Clan","Image":null,"SortOrder":0},"Cost":0,"Rules":"Standard","TROId":440,"TRO":"TR3145","RSId":192,"RS":"None","EraIcon":"https://i.ibb.co/VtCdwyP/era8-10-republic-dark-age.png","DateIntroduced":"3138","EraId":16,"EraStart":3131,"ImageUrl":"https://i.ibb.co/m6nF5X4/black-wolf-3145.png","IsFeatured":false,"IsPublished":true,"Release":1.00,"Type":{"Id":21,"Name":"Infantry","Image":"Infantry.gif","SortOrder":3},"Role":{"Id":104,"Name":"None","Image":null,"SortOrder":0},"BFType":null,"BFSize":0,"BFMove":"","BFTMM":0,"BFArmor":0,"BFStructure":0,"BFThreshold":0,"BFDamageShort":0,"BFDamageMedium":0,"BFDamageLong":0,"BFDamageExtreme":0,"BFOverheat":0,"BFPointValue":0,"BFAbilities":null,"Skill":0,"FormatedTonnage":"1.5"},{"Id":5235,"Name":"Thunderbird Battle Armor \u003cBase\u003e","GroupName":"","Class":"Thunderbird Battle Armor","Variant":"\u003cBase\u003e","Tonnage":1.5,"BattleValue":0,"Technology":{"Id":2,"Name":"Clan","Image":null,"SortOrder":0},"Cost":0,"Rules":"Standard","TROId":226,"TRO":"TR3085S","RSId":192,"RS":"None","EraIcon":"https://i.ibb.co/VtCdwyP/era8-10-republic-dark-age.png","DateIntroduced":"3086","EraId":15,"EraStart":3081,"ImageUrl":"https://i.ibb.co/VS9zz7N/thunderbird-ii-xtr.png","IsFeatured":false,"IsPublished":true,"Release":2.00,"Type":{"Id":21,"Name":"Infantry","Image":"Infantry.gif","SortOrder":3},"Role":{"Id":104,"Name":"None","Image":null,"SortOrder":0},"BFType":null,"BFSize":0,"BFMove":"","BFTMM":0,"BFArmor":0,"BFStructure":0,"BFThreshold":0,"BFDamageShort":0,"BFDamageMedium":0,"BFDamageLong":0,"BFDamageExtreme":0,"BFOverheat":0,"BFPointValue":0,"BFAbilities":null,"Skill":0,"FormatedTonnage":"1.5"},{"Id":7894,"Name":"Thunderbird Battle Armor (Upgrade) \u003cBase\u003e","GroupName":"","Class":"Thunderbird Battle Armor (Upgrade)","Variant":"\u003cBase\u003e","Tonnage":1.5,"BattleValue":0,"Technology":{"Id":2,"Name":"Clan","Image":null,"SortOrder":0},"Cost":0,"Rules":"Standard","TROId":393,"TRO":"RS3145NTNU","RSId":192,"RS":"None","EraIcon":"https://i.ibb.co/VtCdwyP/era8-10-republic-dark-age.png","DateIntroduced":"3089","EraId":15,"EraStart":3081,"ImageUrl":"https://i.ibb.co/VS9zz7N/thunderbird-ii-xtr.png","IsFeatured":false,"IsPublished":true,"Release":2.00,"Type":{"Id":21,"Name":"Infantry","Image":"Infantry.gif","SortOrder":3},"Role":{"Id":104,"Name":"None","Image":null,"SortOrder":0},"BFType":null,"BFSize":0,"BFMove":"0","BFTMM":0,"BFArmor":0,"BFStructure":0,"BFThreshold":0,"BFDamageShort":0,"BFDamageMedium":0,"BFDamageLong":0,"BFDamageExtreme":0,"BFOverheat":0,"BFPointValue":0,"BFAbilities":null,"Skill":0,"FormatedTonnage":"1.5"},{"Id":4124,"Name":"Elemental II Battle Armor X","GroupName":"","Class":"Elemental II Battle Armor","Variant":"X","Tonnage":1.5,"BattleValue":230,"Technology":{"Id":2,"Name":"Clan","Image":null,"SortOrder":0},"Cost":5100400,"Rules":"Experimental","TROId":263,"TRO":"XTRClans","RSId":263,"RS":"XTRClans","EraIcon":"https://i.ibb.co/4jf2wfz/era7-jihad.png","DateIntroduced":"3076","EraId":14,"EraStart":3068,"ImageUrl":"https://i.ibb.co/G00w9Zh/elemental-ii-proto.png","IsFeatured":true,"IsPublished":true,"Release":1.00,"Type":{"Id":21,"Name":"Infantry","Image":"Infantry.gif","SortOrder":3},"Role":{"Id":112,"Name":"Ambusher","Image":null,"SortOrder":1},"BFType":"BA","BFSize":1,"BFMove":"6\"j","BFTMM":0,"BFArmor":1,"BFStructure":2,"BFThreshold":0,"BFDamageShort":2,"BFDamageMedium":0,"BFDamageLong":0,"BFDamageExtreme":0,"BFOverheat":0,"BFPointValue":15,"BFAbilities":"CAR4,MEC","Skill":0,"FormatedTonnage":"1.5"},{"Id":3228,"Name":"Thunderbird Battle Armor [AP Gauss]","GroupName":"","Class":"Thunderbird Battle Armor","Variant":"[AP Gauss]","Tonnage":1.5,"BattleValue":260,"Technology":{"Id":2,"Name":"Clan","Image":null,"SortOrder":0},"Cost":4917500,"Rules":"Standard","TROId":226,"TRO":"TR3085S","RSId":253,"RS":"RS3085u-CE","EraIcon":"https://i.ibb.co/VtCdwyP/era8-10-republic-dark-age.png","DateIntroduced":"3086","EraId":15,"EraStart":3081,"ImageUrl":"https://i.ibb.co/VS9zz7N/thunderbird-ii-xtr.png","IsFeatured":false,"IsPublished":true,"Release":1.00,"Type":{"Id":21,"Name":"Infantry","Image":"Infantry.gif","SortOrder":3},"Role":{"Id":112,"Name":"Ambusher","Image":null,"SortOrder":1},"BFType":"BA","BFSize":1,"BFMove":"6\"j","BFTMM":0,"BFArmor":1,"BFStructure":2,"BFThreshold":0,"BFDamageShort":2,"BFDamageMedium":2,"BFDamageLong":0,"BFDamageExtreme":0,"BFOverheat":0,"BFPointValue":18,"BFAbilities":"CAR4,MEC","Skill":0,"FormatedTonnage":"1.5"},{"Id":3230,"Name":"Thunderbird Battle Armor [Pulse Laser]","GroupName":"","Class":"Thunderbird Battle Armor","Variant":"[Pulse Laser]","Tonnage":1.5,"BattleValue":272,"Technology":{"Id":2,"Name":"Clan","Image":null,"SortOrder":0},"Cost":4947500,"Rules":"Standard","TROId":226,"TRO":"TR3085S","RSId":253,"RS":"RS3085u-CE","EraIcon":"https://i.ibb.co/VtCdwyP/era8-10-republic-dark-age.png","DateIntroduced":"3086","EraId":15,"EraStart":3081,"ImageUrl":"https://i.ibb.co/VS9zz7N/thunderbird-ii-xtr.png","IsFeatured":false,"IsPublished":true,"Release":1.00,"Type":{"Id":21,"Name":"Infantry","Image":"Infantry.gif","SortOrder":3},"Role":{"Id":112,"Name":"Ambusher","Image":null,"SortOrder":1},"BFType":"BA","BFSize":1,"BFMove":"6\"j","BFTMM":0,"BFArmor":1,"BFStructure":2,"BFThreshold":0,"BFDamageShort":2,"BFDamageMedium":2,"BFDamageLong":0,"BFDamageExtreme":0,"BFOverheat":0,"BFPointValue":18,"BFAbilities":"CAR4,MEC","Skill":0,"FormatedTonnage":"1.5"},{"Id":6242,"Name":"Black Wolf Battle Armor [Plasma]","GroupName":"","Class":"Black Wolf Battle Armor","Variant":"[Plasma]","Tonnage":1.5,"BattleValue":280,"Technology":{"Id":2,"Name":"Clan","Image":null,"SortOrder":0},"Cost":3807500,"Rules":"Standard","TROId":440,"TRO":"TR3145","RSId":439,"RS":"RS3145u","EraIcon":"https://i.ibb.co/VtCdwyP/era8-10-republic-dark-age.png","DateIntroduced":"3138","EraId":16,"EraStart":3131,"ImageUrl":"https://i.ibb.co/m6nF5X4/black-wolf-3145.png","IsFeatured":false,"IsPublished":true,"Release":1.00,"Type":{"Id":21,"Name":"Infantry","Image":"Infantry.gif","SortOrder":3},"Role":{"Id":112,"Name":"Ambusher","Image":null,"SortOrder":1},"BFType":"BA","BFSize":1,"BFMove":"2\"j","BFTMM":0,"BFArmor":1,"BFStructure":2,"BFThreshold":0,"BFDamageShort":1,"BFDamageMedium":1,"BFDamageLong":0,"BFDamageExtreme":0,"BFOverheat":0,"BFPointValue":8,"BFAbilities":"CAR4,MEC,RCA","Skill":0,"FormatedTonnage":"1.5"},{"Id":6240,"Name":"Black Wolf Battle Armor [Heavy Flamer]","GroupName":"","Class":"Black Wolf Battle Armor","Variant":"[Heavy Flamer]","Tonnage":1.5,"BattleValue":289,"Technology":{"Id":2,"Name":"Clan","Image":null,"SortOrder":0},"Cost":3723750,"Rules":"Standard","TROId":440,"TRO":"TR3145","RSId":439,"RS":"RS3145u","EraIcon":"https://i.ibb.co/VtCdwyP/era8-10-republic-dark-age.png","DateIntroduced":"3138","EraId":16,"EraStart":3131,"ImageUrl":"https://i.ibb.co/m6nF5X4/black-wolf-3145.png","IsFeatured":false,"IsPublished":true,"Release":1.00,"Type":{"Id":21,"Name":"Infantry","Image":"Infantry.gif","SortOrder":3},"Role":{"Id":112,"Name":"Ambusher","Image":null,"SortOrder":1},"BFType":"BA","BFSize":1,"BFMove":"2\"j","BFTMM":0,"BFArmor":1,"BFStructure":2,"BFThreshold":0,"BFDamageShort":2,"BFDamageMedium":2,"BFDamageLong":0,"BFDamageExtreme":0,"BFOverheat":0,"BFPointValue":12,"BFAbilities":"CAR4,HT2/-/-,MEC,RCA","Skill":0,"FormatedTonnage":"1.5"},{"Id":6241,"Name":"Black Wolf Battle Armor [Heavy Mortar]","GroupName":"","Class":"Black Wolf Battle Armor","Variant":"[Heavy Mortar]","Tonnage":1.5,"BattleValue":294,"Technology":{"Id":2,"Name":"Clan","Image":null,"SortOrder":0},"Cost":3705000,"Rules":"Standard","TROId":440,"TRO":"TR3145","RSId":439,"RS":"RS3145u","EraIcon":"https://i.ibb.co/VtCdwyP/era8-10-republic-dark-age.png","DateIntroduced":"3138","EraId":16,"EraStart":3131,"ImageUrl":"https://i.ibb.co/m6nF5X4/black-wolf-3145.png","IsFeatured":false,"IsPublished":true,"Release":1.00,"Type":{"Id":21,"Name":"Infantry","Image":"Infantry.gif","SortOrder":3},"Role":{"Id":112,"Name":"Ambusher","Image":null,"SortOrder":1},"BFType":"BA","BFSize":1,"BFMove":"2\"j","BFTMM":0,"BFArmor":1,"BFStructure":2,"BFThreshold":0,"BFDamageShort":1,"BFDamageMedium":0,"BFDamageLong":0,"BFDamageExtreme":0,"BFOverheat":0,"BFPointValue":4,"BFAbilities":"CAR4,MEC,RCA","Skill":0,"FormatedTonnage":"1.5"},{"Id":3229,"Name":"Thunderbird Battle Armor [ER Laser]","GroupName":"","Class":"Thunderbird Battle Armor","Variant":"[ER Laser]","Tonnage":1.5,"BattleValue":300,"Technology":{"Id":2,"Name":"Clan","Image":null,"SortOrder":0},"Cost":4923750,"Rules":"Standard","TROId":226,"TRO":"TR3085S","RSId":253,"RS":"RS3085u-CE","EraIcon":"https://i.ibb.co/VtCdwyP/era8-10-republic-dark-age.png","DateIntroduced":"3086","EraId":15,"EraStart":3081,"ImageUrl":"https://i.ibb.co/VS9zz7N/thunderbird-ii-xtr.png","IsFeatured":false,"IsPublished":true,"Release":1.00,"Type":{"Id":21,"Name":"Infantry","Image":"Infantry.gif","SortOrder":3},"Role":{"Id":112,"Name":"Ambusher","Image":null,"SortOrder":1},"BFType":"BA","BFSize":1,"BFMove":"6\"j","BFTMM":0,"BFArmor":1,"BFStructure":2,"BFThreshold":0,"BFDamageShort":2,"BFDamageMedium":2,"BFDamageLong":0,"BFDamageExtreme":0,"BFOverheat":0,"BFPointValue":18,"BFAbilities":"CAR4,MEC","Skill":0,"FormatedTonnage":"1.5"},{"Id":6243,"Name":"Black Wolf Battle Armor [LB-X]","GroupName":"","Class":"Black Wolf Battle Armor","Variant":"[LB-X]","Tonnage":1.5,"BattleValue":303,"Technology":{"Id":2,"Name":"Clan","Image":null,"SortOrder":0},"Cost":0,"Rules":"Standard","TROId":440,"TRO":"TR3145","RSId":439,"RS":"RS3145u","EraIcon":"https://i.ibb.co/VtCdwyP/era8-10-republic-dark-age.png","DateIntroduced":"3138","EraId":16,"EraStart":3131,"ImageUrl":"https://i.ibb.co/m6nF5X4/black-wolf-3145.png","IsFeatured":false,"IsPublished":true,"Release":1.00,"Type":{"Id":21,"Name":"Infantry","Image":"Infantry.gif","SortOrder":3},"Role":{"Id":112,"Name":"Ambusher","Image":null,"SortOrder":1},"BFType":"BA","BFSize":1,"BFMove":"2\"j","BFTMM":0,"BFArmor":1,"BFStructure":2,"BFThreshold":0,"BFDamageShort":2,"BFDamageMedium":2,"BFDamageLong":0,"BFDamageExtreme":0,"BFOverheat":0,"BFPointValue":10,"BFAbilities":"CAR4,FLK1/1/-,MEC,RCA","Skill":0,"FormatedTonnage":"1.5"},{"Id":6737,"Name":"Thunderbird Battle Armor (Upgrade) [LB-X]","GroupName":"","Class":"Thunderbird Battle Armor (Upgrade)","Variant":"[LB-X]","Tonnage":1.5,"BattleValue":323,"Technology":{"Id":2,"Name":"Clan","Image":null,"SortOrder":0},"Cost":0,"Rules":"Standard","TROId":393,"TRO":"RS3145NTNU","RSId":393,"RS":"RS3145NTNU","EraIcon":"https://i.ibb.co/VtCdwyP/era8-10-republic-dark-age.png","DateIntroduced":"3089","EraId":15,"EraStart":3081,"ImageUrl":"https://i.ibb.co/VS9zz7N/thunderbird-ii-xtr.png","IsFeatured":false,"IsPublished":true,"Release":2.00,"Type":{"Id":21,"Name":"Infantry","Image":"Infantry.gif","SortOrder":3},"Role":{"Id":112,"Name":"Ambusher","Image":null,"SortOrder":1},"BFType":"BA","BFSize":1,"BFMove":"6\"j","BFTMM":0,"BFArmor":1,"BFStructure":2,"BFThreshold":0,"BFDamageShort":2,"BFDamageMedium":2,"BFDamageLong":0,"BFDamageExtreme":0,"BFOverheat":0,"BFPointValue":18,"BFAbilities":"CAR4,FLK1/1/-,MEC,RFA","Skill":0,"FormatedTonnage":"1.5"},{"Id":6738,"Name":"Thunderbird Battle Armor (Upgrade) [Pulse Laser]","GroupName":"","Class":"Thunderbird Battle Armor (Upgrade)","Variant":"[Pulse Laser]","Tonnage":1.5,"BattleValue":339,"Technology":{"Id":2,"Name":"Clan","Image":null,"SortOrder":0},"Cost":0,"Rules":"Standard","TROId":393,"TRO":"RS3145NTNU","RSId":393,"RS":"RS3145NTNU","EraIcon":"https://i.ibb.co/VtCdwyP/era8-10-republic-dark-age.png","DateIntroduced":"3089","EraId":15,"EraStart":3081,"ImageUrl":"https://i.ibb.co/VS9zz7N/thunderbird-ii-xtr.png","IsFeatured":false,"IsPublished":true,"Release":2.00,"Type":{"Id":21,"Name":"Infantry","Image":"Infantry.gif","SortOrder":3},"Role":{"Id":112,"Name":"Ambusher","Image":null,"SortOrder":1},"BFType":"BA","BFSize":1,"BFMove":"6\"j","BFTMM":0,"BFArmor":1,"BFStructure":2,"BFThreshold":0,"BFDamageShort":2,"BFDamageMedium":2,"BFDamageLong":0,"BFDamageExtreme":0,"BFOverheat":0,"BFPointValue":18,"BFAbilities":"CAR4,MEC,RFA","Skill":0,"FormatedTonnage":"1.5"},{"Id":7357,"Name":"Thunderbird II Battle Armor (Standard)","GroupName":"","Class":"Thunderbird II Battle Armor","Variant":"(Standard)","Tonnage":1.5,"BattleValue":345,"Technology":{"Id":2,"Name":"Clan","Image":null,"SortOrder":0},"Cost":3735000,"Rules":"Advanced","TROId":415,"TRO":"XTR RotS 2","RSId":415,"RS":"XTR RotS 2","EraIcon":"https://i.ibb.co/VtCdwyP/era8-10-republic-dark-age.png","DateIntroduced":"3133","EraId":16,"EraStart":3131,"ImageUrl":"https://i.ibb.co/VS9zz7N/thunderbird-ii-xtr.png","IsFeatured":true,"IsPublished":true,"Release":1.00,"Type":{"Id":21,"Name":"Infantry","Image":"Infantry.gif","SortOrder":3},"Role":{"Id":112,"Name":"Ambusher","Image":null,"SortOrder":1},"BFType":"BA","BFSize":1,"BFMove":"4\"f","BFTMM":0,"BFArmor":1,"BFStructure":2,"BFThreshold":0,"BFDamageShort":3,"BFDamageMedium":3,"BFDamageLong":0,"BFDamageExtreme":0,"BFOverheat":0,"BFPointValue":18,"BFAbilities":"CAR4,C3S,FLK1/1/-,MEC,MHQ1,RFA","Skill":0,"FormatedTonnage":"1.5"},{"Id":4931,"Name":"Rogue Bear Heavy Battle Armor (Standard)","GroupName":"","Class":"Rogue Bear Heavy Battle Armor","Variant":"(Standard)","Tonnage":1.5,"BattleValue":346,"Technology":{"Id":2,"Name":"Clan","Image":null,"SortOrder":0},"Cost":4755000,"Rules":"Standard","TROId":189,"TRO":"TR3075","RSId":396,"RS":"RS3075u-CE","EraIcon":"https://i.ibb.co/4jf2wfz/era7-jihad.png","DateIntroduced":"3073","EraId":14,"EraStart":3068,"ImageUrl":"https://i.ibb.co/8jNGpVk/rogue-bear-3075.png","IsFeatured":true,"IsPublished":true,"Release":1.30,"Type":{"Id":21,"Name":"Infantry","Image":"Infantry.gif","SortOrder":3},"Role":{"Id":112,"Name":"Ambusher","Image":null,"SortOrder":1},"BFType":"BA","BFSize":1,"BFMove":"4\"j","BFTMM":0,"BFArmor":2,"BFStructure":2,"BFThreshold":0,"BFDamageShort":3,"BFDamageMedium":2,"BFDamageLong":0,"BFDamageExtreme":0,"BFOverheat":0,"BFPointValue":13,"BFAbilities":"CAR4,MEC","Skill":0,"FormatedTonnage":"1.5"},{"Id":6239,"Name":"Black Wolf Battle Armor [ERSPL]","GroupName":"","Class":"Black Wolf Battle Armor","Variant":"[ERSPL]","Tonnage":1.5,"BattleValue":348,"Technology":{"Id":2,"Name":"Clan","Image":null,"SortOrder":0},"Cost":3817500,"Rules":"Standard","TROId":440,"TRO":"TR3145","RSId":439,"RS":"RS3145u","EraIcon":"https://i.ibb.co/VtCdwyP/era8-10-republic-dark-age.png","DateIntroduced":"3138","EraId":16,"EraStart":3131,"ImageUrl":"https://i.ibb.co/m6nF5X4/black-wolf-3145.png","IsFeatured":false,"IsPublished":true,"Release":1.00,"Type":{"Id":21,"Name":"Infantry","Image":"Infantry.gif","SortOrder":3},"Role":{"Id":112,"Name":"Ambusher","Image":null,"SortOrder":1},"BFType":"BA","BFSize":1,"BFMove":"2\"j","BFTMM":0,"BFArmor":1,"BFStructure":2,"BFThreshold":0,"BFDamageShort":2,"BFDamageMedium":2,"BFDamageLong":0,"BFDamageExtreme":0,"BFOverheat":0,"BFPointValue":10,"BFAbilities":"CAR4,MEC,RCA","Skill":0,"FormatedTonnage":"1.5"},{"Id":1217,"Name":"Gnome Battle Armor (Upgrade) [Bearhunter]","GroupName":"","Class":"Gnome Battle Armor","Variant":"(Upgrade) [Bearhunter]","Tonnage":1.5,"BattleValue":354,"Technology":{"Id":2,"Name":"Clan","Image":null,"SortOrder":0},"Cost":4807500,"Rules":"Standard","TROId":240,"TRO":"TR3058U","RSId":255,"RS":"RS3058Uu-C","EraIcon":"https://i.ibb.co/4jf2wfz/era7-jihad.png","DateIntroduced":"3069","EraId":14,"EraStart":3068,"ImageUrl":"https://i.ibb.co/YW015j5/gnome-3058u.png","IsFeatured":false,"IsPublished":true,"Release":1.00,"Type":{"Id":21,"Name":"Infantry","Image":"Infantry.gif","SortOrder":3},"Role":{"Id":108,"Name":"Juggernaut","Image":null,"SortOrder":3},"BFType":"BA","BFSize":1,"BFMove":"4\"j","BFTMM":0,"BFArmor":2,"BFStructure":2,"BFThreshold":0,"BFDamageShort":4,"BFDamageMedium":2,"BFDamageLong":0,"BFDamageExtreme":0,"BFOverheat":0,"BFPointValue":14,"BFAbilities":"CAR4,MEC","Skill":0,"FormatedTonnage":"1.5"},{"Id":6736,"Name":"Thunderbird Battle Armor (Upgrade) [ER Laser]","GroupName":"","Class":"Thunderbird Battle Armor (Upgrade)","Variant":"[ER Laser]","Tonnage":1.5,"BattleValue":367,"Technology":{"Id":2,"Name":"Clan","Image":null,"SortOrder":0},"Cost":0,"Rules":"Standard","TROId":393,"TRO":"RS3145NTNU","RSId":393,"RS":"RS3145NTNU","EraIcon":"https://i.ibb.co/VtCdwyP/era8-10-republic-dark-age.png","DateIntroduced":"3089","EraId":15,"EraStart":3081,"ImageUrl":"https://i.ibb.co/VS9zz7N/thunderbird-ii-xtr.png","IsFeatured":false,"IsPublished":true,"Release":2.00,"Type":{"Id":21,"Name":"Infantry","Image":"Infantry.gif","SortOrder":3},"Role":{"Id":112,"Name":"Ambusher","Image":null,"SortOrder":1},"BFType":"BA","BFSize":1,"BFMove":"6\"j","BFTMM":0,"BFArmor":1,"BFStructure":2,"BFThreshold":0,"BFDamageShort":2,"BFDamageMedium":2,"BFDamageLong":0,"BFDamageExtreme":0,"BFOverheat":0,"BFPointValue":18,"BFAbilities":"CAR4,MEC,RFA","Skill":0,"FormatedTonnage":"1.5"},{"Id":4005,"Name":"Corona Heavy Battle Armor (SRM)","GroupName":"","Class":"Corona Heavy Battle Armor","Variant":"(SRM)","Tonnage":1.5,"BattleValue":373,"Technology":{"Id":2,"Name":"Clan","Image":null,"SortOrder":0},"Cost":2947900,"Rules":"Standard","TROId":189,"TRO":"TR3075","RSId":396,"RS":"RS3075u-CE","EraIcon":"https://i.ibb.co/4jf2wfz/era7-jihad.png","DateIntroduced":"3073","EraId":14,"EraStart":3068,"ImageUrl":"https://i.ibb.co/r69szJZ/corona-3075.png","IsFeatured":false,"IsPublished":true,"Release":1.30,"Type":{"Id":21,"Name":"Infantry","Image":"Infantry.gif","SortOrder":3},"Role":{"Id":112,"Name":"Ambusher","Image":null,"SortOrder":1},"BFType":"BA","BFSize":1,"BFMove":"4\"f","BFTMM":0,"BFArmor":1,"BFStructure":2,"BFThreshold":0,"BFDamageShort":4,"BFDamageMedium":3,"BFDamageLong":0,"BFDamageExtreme":0,"BFOverheat":0,"BFPointValue":14,"BFAbilities":"CAR4,HT1/-/-,MEC","Skill":0,"FormatedTonnage":"1.5"},{"Id":1218,"Name":"Gnome Battle Armor (Upgrade) [MRR]","GroupName":"","Class":"Gnome Battle Armor","Variant":"(Upgrade) [MRR]","Tonnage":1.5,"BattleValue":391,"Technology":{"Id":2,"Name":"Clan","Image":null,"SortOrder":0},"Cost":4852500,"Rules":"Standard","TROId":240,"TRO":"TR3058U","RSId":255,"RS":"RS3058Uu-C","EraIcon":"https://i.ibb.co/4jf2wfz/era7-jihad.png","DateIntroduced":"3069","EraId":14,"EraStart":3068,"ImageUrl":"https://i.ibb.co/YW015j5/gnome-3058u.png","IsFeatured":false,"IsPublished":true,"Release":1.00,"Type":{"Id":21,"Name":"Infantry","Image":"Infantry.gif","SortOrder":3},"Role":{"Id":108,"Name":"Juggernaut","Image":null,"SortOrder":3},"BFType":"BA","BFSize":1,"BFMove":"4\"j","BFTMM":0,"BFArmor":2,"BFStructure":2,"BFThreshold":0,"BFDamageShort":3,"BFDamageMedium":3,"BFDamageLong":0,"BFDamageExtreme":0,"BFOverheat":0,"BFPointValue":15,"BFAbilities":"CAR4,MEC","Skill":0,"FormatedTonnage":"1.5"},{"Id":6734,"Name":"Rogue Bear Heavy Battle Armor (Upgrade)","GroupName":"","Class":"Rogue Bear Heavy Battle Armor","Variant":"(Upgrade)","Tonnage":1.5,"BattleValue":396,"Technology":{"Id":2,"Name":"Clan","Image":null,"SortOrder":0},"Cost":4840000,"Rules":"Standard","TROId":393,"TRO":"RS3145NTNU","RSId":393,"RS":"RS3145NTNU","EraIcon":"https://i.ibb.co/VtCdwyP/era8-10-republic-dark-age.png","DateIntroduced":"3108","EraId":254,"EraStart":3101,"ImageUrl":"https://i.ibb.co/8jNGpVk/rogue-bear-3075.png","IsFeatured":false,"IsPublished":true,"Release":1.30,"Type":{"Id":21,"Name":"Infantry","Image":"Infantry.gif","SortOrder":3},"Role":{"Id":108,"Name":"Juggernaut","Image":null,"SortOrder":3},"BFType":"BA","BFSize":1,"BFMove":"4\"j","BFTMM":0,"BFArmor":2,"BFStructure":2,"BFThreshold":0,"BFDamageShort":2,"BFDamageMedium":1,"BFDamageLong":0,"BFDamageExtreme":0,"BFOverheat":0,"BFPointValue":11,"BFAbilities":"CAR4,MEC,RCA","Skill":0,"FormatedTonnage":"1.5"},{"Id":1219,"Name":"Gnome Battle Armor (Upgrade) [Pulse Laser]","GroupName":"","Class":"Gnome Battle Armor","Variant":"(Upgrade) [Pulse Laser]","Tonnage":1.5,"BattleValue":408,"Technology":{"Id":2,"Name":"Clan","Image":null,"SortOrder":0},"Cost":4932500,"Rules":"Standard","TROId":240,"TRO":"TR3058U","RSId":255,"RS":"RS3058Uu-C","EraIcon":"https://i.ibb.co/4jf2wfz/era7-jihad.png","DateIntroduced":"3069","EraId":14,"EraStart":3068,"ImageUrl":"https://i.ibb.co/YW015j5/gnome-3058u.png","IsFeatured":false,"IsPublished":true,"Release":1.00,"Type":{"Id":21,"Name":"Infantry","Image":"Infantry.gif","SortOrder":3},"Role":{"Id":108,"Name":"Juggernaut","Image":null,"SortOrder":3},"BFType":"BA","BFSize":1,"BFMove":"4\"j","BFTMM":0,"BFArmor":2,"BFStructure":2,"BFThreshold":0,"BFDamageShort":4,"BFDamageMedium":2,"BFDamageLong":0,"BFDamageExtreme":0,"BFOverheat":0,"BFPointValue":14,"BFAbilities":"CAR4,MEC","Skill":0,"FormatedTonnage":"1.5"},{"Id":1216,"Name":"Gnome Battle Armor (Standard)","GroupName":"","Class":"Gnome Battle Armor","Variant":"(Standard)","Tonnage":1.5,"BattleValue":431,"Technology":{"Id":2,"Name":"Clan","Image":null,"SortOrder":0},"Cost":4863750,"Rules":"Standard","TROId":240,"TRO":"TR3058U","RSId":255,"RS":"RS3058Uu-C","EraIcon":"https://i.ibb.co/k6ySqKN/era5-clan-invasion.png","DateIntroduced":"3056","EraId":13,"EraStart":3050,"ImageUrl":"https://i.ibb.co/YW015j5/gnome-3058u.png","IsFeatured":true,"IsPublished":true,"Release":1.00,"Type":{"Id":21,"Name":"Infantry","Image":"Infantry.gif","SortOrder":3},"Role":{"Id":108,"Name":"Juggernaut","Image":null,"SortOrder":3},"BFType":"BA","BFSize":1,"BFMove":"4\"j","BFTMM":0,"BFArmor":2,"BFStructure":2,"BFThreshold":0,"BFDamageShort":3,"BFDamageMedium":3,"BFDamageLong":0,"BFDamageExtreme":0,"BFOverheat":0,"BFPointValue":15,"BFAbilities":"CAR4,MEC","Skill":0,"FormatedTonnage":"1.5"},{"Id":1215,"Name":"Gnome Battle Armor (LRM)","GroupName":"","Class":"Gnome Battle Armor","Variant":"(LRM)","Tonnage":1.5,"BattleValue":454,"Technology":{"Id":2,"Name":"Clan","Image":null,"SortOrder":0},"Cost":4827500,"Rules":"Standard","TROId":202,"TRO":"TR3085","RSId":257,"RS":"RS3085u-ONN","EraIcon":"https://i.ibb.co/4jf2wfz/era7-jihad.png","DateIntroduced":"3073","EraId":14,"EraStart":3068,"ImageUrl":"https://i.ibb.co/YW015j5/gnome-3058u.png","IsFeatured":false,"IsPublished":true,"Release":1.00,"Type":{"Id":21,"Name":"Infantry","Image":"Infantry.gif","SortOrder":3},"Role":{"Id":110,"Name":"Missile Boat","Image":null,"SortOrder":4},"BFType":"BA","BFSize":1,"BFMove":"4\"j","BFTMM":0,"BFArmor":2,"BFStructure":2,"BFThreshold":0,"BFDamageShort":2,"BFDamageMedium":2,"BFDamageLong":1,"BFDamageExtreme":0,"BFOverheat":0,"BFPointValue":19,"BFAbilities":"CAR4,IF1,MEC","Skill":0,"FormatedTonnage":"1.5"},{"Id":4912,"Name":"Rhino Battle Armor (Standard)","GroupName":"","Class":"Rhino Battle Armor","Variant":"(Standard)","Tonnage":1.5,"BattleValue":473,"Technology":{"Id":2,"Name":"Clan","Image":null,"SortOrder":0},"Cost":0,"Rules":"Standard","TROId":445,"TRO":"TRGC","RSId":445,"RS":"TRGC","EraIcon":"https://i.ibb.co/MB09bVm/era3-4-succession-wars.png","DateIntroduced":"2871","EraId":11,"EraStart":2781,"ImageUrl":"https://i.ibb.co/YW015j5/gnome-3058u.png","IsFeatured":true,"IsPublished":true,"Release":1.10,"Type":{"Id":21,"Name":"Infantry","Image":"Infantry.gif","SortOrder":3},"Role":{"Id":104,"Name":"None","Image":null,"SortOrder":0},"BFType":null,"BFSize":0,"BFMove":"","BFTMM":0,"BFArmor":0,"BFStructure":0,"BFThreshold":0,"BFDamageShort":0,"BFDamageMedium":0,"BFDamageLong":0,"BFDamageExtreme":0,"BFOverheat":0,"BFPointValue":0,"BFAbilities":null,"Skill":0,"FormatedTonnage":"1.5"},{"Id":4006,"Name":"Corona Heavy Battle Armor (Standard)","GroupName":"","Class":"Corona Heavy Battle Armor","Variant":"(Standard)","Tonnage":1.5,"BattleValue":495,"Technology":{"Id":2,"Name":"Clan","Image":null,"SortOrder":0},"Cost":3060400,"Rules":"Standard","TROId":189,"TRO":"TR3075","RSId":396,"RS":"RS3075u-CE","EraIcon":"https://i.ibb.co/k6ySqKN/era5-clan-invasion.png","DateIntroduced":"3060","EraId":13,"EraStart":3050,"ImageUrl":"https://i.ibb.co/r69szJZ/corona-3075.png","IsFeatured":false,"IsPublished":true,"Release":1.30,"Type":{"Id":21,"Name":"Infantry","Image":"Infantry.gif","SortOrder":3},"Role":{"Id":112,"Name":"Ambusher","Image":null,"SortOrder":1},"BFType":"BA","BFSize":1,"BFMove":"4\"f","BFTMM":0,"BFArmor":1,"BFStructure":2,"BFThreshold":0,"BFDamageShort":3,"BFDamageMedium":3,"BFDamageLong":0,"BFDamageExtreme":0,"BFOverheat":0,"BFPointValue":12,"BFAbilities":"CAR4,MEC","Skill":0,"FormatedTonnage":"1.5"},{"Id":6587,"Name":"Cuchulainn Support Armor (Standard)","GroupName":"","Class":"Cuchulainn Support Armor","Variant":"(Standard)","Tonnage":1.5,"BattleValue":621,"Technology":{"Id":2,"Name":"Clan","Image":null,"SortOrder":0},"Cost":0,"Rules":"Standard","TROId":441,"TRO":"TR3150","RSId":439,"RS":"RS3145u","EraIcon":"https://i.ibb.co/VtCdwyP/era8-10-republic-dark-age.png","DateIntroduced":"3134","EraId":16,"EraStart":3131,"ImageUrl":"https://i.ibb.co/DpSR8XY/cuchulainn-3150.png","IsFeatured":true,"IsPublished":true,"Release":1.00,"Type":{"Id":21,"Name":"Infantry","Image":"Infantry.gif","SortOrder":3},"Role":{"Id":108,"Name":"Juggernaut","Image":null,"SortOrder":3},"BFType":"BA","BFSize":1,"BFMove":"4\"f","BFTMM":0,"BFArmor":2,"BFStructure":2,"BFThreshold":0,"BFDamageShort":3,"BFDamageMedium":3,"BFDamageLong":0,"BFDamageExtreme":0,"BFOverheat":0,"BFPointValue":14,"BFAbilities":"CAR4,MEC,STL","Skill":0,"FormatedTonnage":"1.5"},{"Id":4222,"Name":"Golem Assault Armor (Fast Assault)","GroupName":"","Class":"Golem Assault Armor","Variant":"(Fast Assault)","Tonnage":2,"BattleValue":367,"Technology":{"Id":2,"Name":"Clan","Image":null,"SortOrder":0},"Cost":8007900,"Rules":"Standard","TROId":189,"TRO":"TR3075","RSId":396,"RS":"RS3075u-CE","EraIcon":"https://i.ibb.co/4jf2wfz/era7-jihad.png","DateIntroduced":"3072","EraId":14,"EraStart":3068,"ImageUrl":"https://i.ibb.co/wYp49T6/golem-3075.png","IsFeatured":false,"IsPublished":true,"Release":1.30,"Type":{"Id":21,"Name":"Infantry","Image":"Infantry.gif","SortOrder":3},"Role":{"Id":108,"Name":"Juggernaut","Image":null,"SortOrder":3},"BFType":"BA","BFSize":1,"BFMove":"6\"j","BFTMM":0,"BFArmor":2,"BFStructure":2,"BFThreshold":0,"BFDamageShort":2,"BFDamageMedium":0,"BFDamageLong":0,"BFDamageExtreme":0,"BFOverheat":0,"BFPointValue":18,"BFAbilities":"CAR4","Skill":0,"FormatedTonnage":"2"},{"Id":1623,"Name":"Ironhold Assault Battle Armor (Standard)","GroupName":"","Class":"Ironhold Assault Battle Armor","Variant":"(Standard)","Tonnage":2,"BattleValue":398,"Technology":{"Id":2,"Name":"Clan","Image":null,"SortOrder":0},"Cost":7535000,"Rules":"Standard","TROId":202,"TRO":"TR3085","RSId":253,"RS":"RS3085u-CE","EraIcon":"https://i.ibb.co/4jf2wfz/era7-jihad.png","DateIntroduced":"3077","EraId":14,"EraStart":3068,"ImageUrl":"https://i.ibb.co/51WMm4K/ironhold-3085.png","IsFeatured":true,"IsPublished":true,"Release":1.00,"Type":{"Id":21,"Name":"Infantry","Image":"Infantry.gif","SortOrder":3},"Role":{"Id":108,"Name":"Juggernaut","Image":null,"SortOrder":3},"BFType":"BA","BFSize":1,"BFMove":"4\"j","BFTMM":0,"BFArmor":2,"BFStructure":2,"BFThreshold":0,"BFDamageShort":3,"BFDamageMedium":3,"BFDamageLong":0,"BFDamageExtreme":0,"BFOverheat":0,"BFPointValue":15,"BFAbilities":"CAR4","Skill":0,"FormatedTonnage":"2"},{"Id":6742,"Name":"Ironhold Assault Battle Armor (Anti-Tank)","GroupName":"","Class":"Ironhold Assault Battle Armor","Variant":"(Anti-Tank)","Tonnage":2,"BattleValue":447,"Technology":{"Id":2,"Name":"Clan","Image":null,"SortOrder":0},"Cost":4847500,"Rules":"Standard","TROId":393,"TRO":"RS3145NTNU","RSId":393,"RS":"RS3145NTNU","EraIcon":"https://i.ibb.co/VtCdwyP/era8-10-republic-dark-age.png","DateIntroduced":"3097","EraId":15,"EraStart":3081,"ImageUrl":"https://i.ibb.co/51WMm4K/ironhold-3085.png","IsFeatured":false,"IsPublished":true,"Release":1.00,"Type":{"Id":21,"Name":"Infantry","Image":"Infantry.gif","SortOrder":3},"Role":{"Id":108,"Name":"Juggernaut","Image":null,"SortOrder":3},"BFType":"BA","BFSize":1,"BFMove":"2\"f","BFTMM":0,"BFArmor":2,"BFStructure":2,"BFThreshold":0,"BFDamageShort":3,"BFDamageMedium":3,"BFDamageLong":0,"BFDamageExtreme":0,"BFOverheat":0,"BFPointValue":14,"BFAbilities":"CAR4,FLK2/2/-,FR","Skill":0,"FormatedTonnage":"2"},{"Id":3478,"Name":"Warg Assault Battle Armor (Standard)","GroupName":"","Class":"Warg Assault Battle Armor","Variant":"(Standard)","Tonnage":2,"BattleValue":486,"Technology":{"Id":2,"Name":"Clan","Image":null,"SortOrder":0},"Cost":4500000,"Rules":"Standard","TROId":226,"TRO":"TR3085S","RSId":253,"RS":"RS3085u-CE","EraIcon":"https://i.ibb.co/VtCdwyP/era8-10-republic-dark-age.png","DateIntroduced":"3086","EraId":15,"EraStart":3081,"ImageUrl":"https://i.ibb.co/PxtBtTt/warg-3085.png","IsFeatured":true,"IsPublished":true,"Release":1.00,"Type":{"Id":21,"Name":"Infantry","Image":"Infantry.gif","SortOrder":3},"Role":{"Id":108,"Name":"Juggernaut","Image":null,"SortOrder":3},"BFType":"BA","BFSize":1,"BFMove":"2\"f","BFTMM":0,"BFArmor":2,"BFStructure":2,"BFThreshold":0,"BFDamageShort":4,"BFDamageMedium":4,"BFDamageLong":0,"BFDamageExtreme":0,"BFOverheat":0,"BFPointValue":16,"BFAbilities":"CAR4","Skill":0,"FormatedTonnage":"2"},{"Id":4223,"Name":"Golem Assault Armor (Rock Golem)","GroupName":"","Class":"Golem Assault Armor","Variant":"(Rock Golem)","Tonnage":2,"BattleValue":545,"Technology":{"Id":2,"Name":"Clan","Image":null,"SortOrder":0},"Cost":4675000,"Rules":"Advanced","TROId":189,"TRO":"TR3075","RSId":396,"RS":"RS3075u-CE","EraIcon":"https://i.ibb.co/4jf2wfz/era7-jihad.png","DateIntroduced":"3072","EraId":14,"EraStart":3068,"ImageUrl":"https://i.ibb.co/wYp49T6/golem-3075.png","IsFeatured":false,"IsPublished":true,"Release":1.30,"Type":{"Id":21,"Name":"Infantry","Image":"Infantry.gif","SortOrder":3},"Role":{"Id":108,"Name":"Juggernaut","Image":null,"SortOrder":3},"BFType":"BA","BFSize":1,"BFMove":"4\"f","BFTMM":0,"BFArmor":2,"BFStructure":2,"BFThreshold":0,"BFDamageShort":3,"BFDamageMedium":3,"BFDamageLong":0,"BFDamageExtreme":0,"BFOverheat":0,"BFPointValue":14,"BFAbilities":"CAR4,FR","Skill":0,"FormatedTonnage":"2"},{"Id":1622,"Name":"Ironhold Assault Battle Armor (Fire)","GroupName":"","Class":"Ironhold Assault Battle Armor","Variant":"(Fire)","Tonnage":2,"BattleValue":562,"Technology":{"Id":2,"Name":"Clan","Image":null,"SortOrder":0},"Cost":4335000,"Rules":"Standard","TROId":202,"TRO":"TR3085","RSId":253,"RS":"RS3085u-CE","EraIcon":"https://i.ibb.co/VtCdwyP/era8-10-republic-dark-age.png","DateIntroduced":"3082","EraId":15,"EraStart":3081,"ImageUrl":"https://i.ibb.co/51WMm4K/ironhold-3085.png","IsFeatured":false,"IsPublished":true,"Release":1.00,"Type":{"Id":21,"Name":"Infantry","Image":"Infantry.gif","SortOrder":3},"Role":{"Id":108,"Name":"Juggernaut","Image":null,"SortOrder":3},"BFType":"BA","BFSize":1,"BFMove":"2\"f","BFTMM":0,"BFArmor":2,"BFStructure":2,"BFThreshold":0,"BFDamageShort":5,"BFDamageMedium":5,"BFDamageLong":0,"BFDamageExtreme":0,"BFOverheat":0,"BFPointValue":19,"BFAbilities":"CAR4,FR","Skill":0,"FormatedTonnage":"2"},{"Id":6748,"Name":"Warg Assault Battle Armor (Reactive)","GroupName":"","Class":"Warg Assault Battle Armor","Variant":"(Reactive)","Tonnage":2,"BattleValue":563,"Technology":{"Id":2,"Name":"Clan","Image":null,"SortOrder":0},"Cost":4625000,"Rules":"Standard","TROId":393,"TRO":"RS3145NTNU","RSId":393,"RS":"RS3145NTNU","EraIcon":"https://i.ibb.co/VtCdwyP/era8-10-republic-dark-age.png","DateIntroduced":"3122","EraId":254,"EraStart":3101,"ImageUrl":"https://i.ibb.co/PxtBtTt/warg-3085.png","IsFeatured":false,"IsPublished":true,"Release":1.00,"Type":{"Id":21,"Name":"Infantry","Image":"Infantry.gif","SortOrder":3},"Role":{"Id":108,"Name":"Juggernaut","Image":null,"SortOrder":3},"BFType":"BA","BFSize":1,"BFMove":"2\"f","BFTMM":0,"BFArmor":2,"BFStructure":2,"BFThreshold":0,"BFDamageShort":4,"BFDamageMedium":4,"BFDamageLong":0,"BFDamageExtreme":0,"BFOverheat":0,"BFPointValue":16,"BFAbilities":"CAR4,RCA","Skill":0,"FormatedTonnage":"2"},{"Id":4224,"Name":"Golem Assault Armor (Standard)","GroupName":"","Class":"Golem Assault Armor","Variant":"(Standard)","Tonnage":2,"BattleValue":650,"Technology":{"Id":2,"Name":"Clan","Image":null,"SortOrder":0},"Cost":4757500,"Rules":"Standard","TROId":189,"TRO":"TR3075","RSId":396,"RS":"RS3075u-CE","EraIcon":"https://i.ibb.co/QjhjKwr/era6-civil-war.png","DateIntroduced":"3067","EraId":247,"EraStart":3062,"ImageUrl":"https://i.ibb.co/wYp49T6/golem-3075.png","IsFeatured":false,"IsPublished":true,"Release":1.30,"Type":{"Id":21,"Name":"Infantry","Image":"Infantry.gif","SortOrder":3},"Role":{"Id":108,"Name":"Juggernaut","Image":null,"SortOrder":3},"BFType":"BA","BFSize":1,"BFMove":"4\"f","BFTMM":0,"BFArmor":2,"BFStructure":2,"BFThreshold":0,"BFDamageShort":4,"BFDamageMedium":2,"BFDamageLong":0,"BFDamageExtreme":0,"BFOverheat":0,"BFPointValue":14,"BFAbilities":"CAR4,FR","Skill":0,"FormatedTonnage":"2"},{"Id":1228,"Name":"Golem Assault Armor (Support)","GroupName":"","Class":"Golem Assault Armor","Variant":"(Support)","Tonnage":2,"BattleValue":685,"Technology":{"Id":2,"Name":"Clan","Image":null,"SortOrder":0},"Cost":4833300,"Rules":"Standard","TROId":202,"TRO":"TR3085","RSId":257,"RS":"RS3085u-ONN","EraIcon":"https://i.ibb.co/4jf2wfz/era7-jihad.png","DateIntroduced":"3076","EraId":14,"EraStart":3068,"ImageUrl":"https://i.ibb.co/wYp49T6/golem-3075.png","IsFeatured":false,"IsPublished":true,"Release":1.00,"Type":{"Id":21,"Name":"Infantry","Image":"Infantry.gif","SortOrder":3},"Role":{"Id":108,"Name":"Juggernaut","Image":null,"SortOrder":3},"BFType":"BA","BFSize":1,"BFMove":"4\"f","BFTMM":0,"BFArmor":2,"BFStructure":2,"BFThreshold":0,"BFDamageShort":3,"BFDamageMedium":3,"BFDamageLong":0,"BFDamageExtreme":0,"BFOverheat":0,"BFPointValue":14,"BFAbilities":"CAR4,FR","Skill":0,"FormatedTonnage":"2"}],"Search":"?Types=21\u0026SubTypes=28\u0026Technologies=2","Crumbs":[{"Name":"Types","Value":"Infantry"},{"Name":"Sub Types","Value":"Battle Armor"},{"Name":"Techs","Value":"Clan"}]}