{"Id":1173,"Name":"Gallant GLT-7-0","GroupName":null,"Class":"Gallant","Variant":"GLT-7-0","Tonnage":70,"BattleValue":1436,"Technology":{"Id":1,"Name":"Inner Sphere","Image":null,"SortOrder":0},"Cost":12062520,"Rules":"Standard","TROId":514,"TRO":"TRDA","RSId":253,"RS":"RS3085u-CE","EraIcon":"https://i.ibb.co/4jf2wfz/era05-jihad.png","DateIntroduced":"3078","EraId":14,"EraStart":3068,"ImageUrl":"https://i.ibb.co/PZN3scW/gallant-3075.png","IsFeatured":true,"IsPublished":true,"Release":1.00,"Type":{"Id":18,"Name":"BattleMech","Image":"BattleMech.gif","SortOrder":0},"Role":{"Id":107,"Name":"Skirmisher","Image":null,"SortOrder":5},"BFType":"BM","BFSize":3,"BFMove":"6\"/10\"j","BFTMM":1,"BFArmor":7,"BFStructure":3,"BFThreshold":0,"BFDamageShort":4,"BFDamageShortMin":false,"BFDamageMedium":4,"BFDamageMediumMin":false,"BFDamageLong":0,"BFDamageLongMin":false,"BFDamageExtreme":0,"BFDamageExtemeMin":false,"BFOverheat":0,"BFPointValue":34,"BFAbilities":"JMPS1","Skill":4,"FormatedTonnage":"70"}