{"Id":1354,"Name":"Ha Otoko 3","GroupName":null,"Class":"Ha Otoko","Variant":"3","Tonnage":65,"BattleValue":2206,"Technology":{"Id":2,"Name":"Clan","Image":null,"SortOrder":0},"Cost":7725410,"Rules":"Standard","TROId":202,"TRO":"TR3085","RSId":257,"RS":"RS3085u-ONN","EraIcon":"https://i.ibb.co/VtCdwyP/era06-republic-dark-age.png","DateIntroduced":"3082","EraId":15,"EraStart":3081,"ImageUrl":"https://i.ibb.co/XDPGX3F/ha-otoko-3060.png","IsFeatured":false,"IsPublished":true,"Release":1.00,"Type":{"Id":18,"Name":"BattleMech","Image":"BattleMech.gif","SortOrder":0},"Role":{"Id":110,"Name":"Missile Boat","Image":null,"SortOrder":4},"BFType":"BM","BFSize":3,"BFMove":"8\"","BFTMM":1,"BFArmor":7,"BFStructure":5,"BFThreshold":0,"BFDamageShort":5,"BFDamageMedium":5,"BFDamageLong":5,"BFDamageExtreme":0,"BFOverheat":1,"BFPointValue":50,"BFAbilities":"CASE,ECM,IF3","Skill":4,"FormatedTonnage":"65"}