{"Id":1633,"Name":"Ishtar Heavy Fire Support Tank (Gauss)","GroupName":null,"Class":"Ishtar Heavy Fire Support Tank","Variant":"(Gauss)","Tonnage":65,"BattleValue":1616,"Technology":{"Id":2,"Name":"Clan","Image":null,"SortOrder":0},"Cost":3280479,"Rules":"Standard","TROId":229,"TRO":"TR3060","RSId":222,"RS":"RS3060u","EraIcon":"https://i.ibb.co/4jf2wfz/era05-jihad.png","DateIntroduced":"3068","EraId":14,"EraStart":3068,"ImageUrl":"https://i.ibb.co/Qd6d3CF/ishtar-3060.png","IsFeatured":false,"IsPublished":true,"Release":1.00,"Type":{"Id":19,"Name":"Combat Vehicle","Image":"CombatVehicle.gif","SortOrder":1},"Role":{"Id":111,"Name":"Sniper","Image":null,"SortOrder":7},"BFType":"CV","BFSize":3,"BFMove":"6\"w","BFTMM":1,"BFArmor":5,"BFStructure":4,"BFThreshold":0,"BFDamageShort":6,"BFDamageShortMin":false,"BFDamageMedium":6,"BFDamageMediumMin":false,"BFDamageLong":4,"BFDamageLongMin":false,"BFDamageExtreme":0,"BFDamageExtemeMin":false,"BFOverheat":0,"BFPointValue":38,"BFAbilities":"CASE,FLK1/1/1,IF1,SRCH,TUR(3/3/3,FLK1/1/1)","Skill":4,"FormatedTonnage":"65"}