{"Id":2034,"Name":"Marauder MAD-2R","GroupName":null,"Class":"Marauder","Variant":"MAD-2R","Tonnage":75,"BattleValue":1630,"Technology":{"Id":1,"Name":"Inner Sphere","Image":null,"SortOrder":0},"Cost":7403375,"Rules":"Standard","TROId":189,"TRO":"TR:3075","RSId":228,"RS":"RS:3075u-AW","EraIcon":"https://i.ibb.co/fr2Wdf0/era01-age-of-war-star-league.png","DateIntroduced":"2760","EraId":10,"EraStart":2571,"ImageUrl":"https://i.ibb.co/rps20YY/marauder-rg.png","IsFeatured":false,"IsPublished":true,"Release":1.00,"Type":{"Id":18,"Name":"BattleMech","Image":"BattleMech.gif","SortOrder":0},"Role":{"Id":111,"Name":"Sniper","Image":null,"SortOrder":7},"BFType":"BM","BFSize":3,"BFMove":"8\"","BFTMM":1,"BFArmor":7,"BFStructure":6,"BFThreshold":0,"BFDamageShort":4,"BFDamageShortMin":false,"BFDamageMedium":4,"BFDamageMediumMin":false,"BFDamageLong":3,"BFDamageLongMin":false,"BFDamageExtreme":0,"BFDamageExtemeMin":false,"BFOverheat":0,"BFPointValue":40,"BFAbilities":"CASE","Skill":4,"FormatedTonnage":"75"}