{"Id":2572,"Name":"Preta C-PRT-O (Kendali)","GroupName":null,"Class":"Preta","Variant":"C-PRT-O (Kendali)","Tonnage":45,"BattleValue":999,"Technology":{"Id":1,"Name":"Inner Sphere","Image":null,"SortOrder":0},"Cost":11968572,"Rules":"Advanced","TROId":208,"TRO":"SBW\u0026B","RSId":208,"RS":"SBW\u0026B","EraIcon":"https://i.ibb.co/4jf2wfz/era05-jihad.png","DateIntroduced":"3071","EraId":14,"EraStart":3068,"ImageUrl":"https://i.ibb.co/1LcZLxc/preta-invictus-3075.png","IsFeatured":false,"IsPublished":true,"Release":1.00,"Type":{"Id":18,"Name":"BattleMech","Image":"BattleMech.gif","SortOrder":0},"Role":{"Id":105,"Name":"Scout","Image":null,"SortOrder":6},"BFType":"BM","BFSize":2,"BFMove":"12\"/16\"j","BFTMM":2,"BFArmor":5,"BFStructure":2,"BFThreshold":0,"BFDamageShort":1,"BFDamageShortMin":false,"BFDamageMedium":1,"BFDamageMediumMin":false,"BFDamageLong":1,"BFDamageLongMin":false,"BFDamageExtreme":0,"BFDamageExtemeMin":false,"BFOverheat":0,"BFPointValue":27,"BFAbilities":"C3I,ENE,JMPS1,MHQ2,OMNI,TAG","Skill":4,"FormatedTonnage":"45"}