{"Id":2673,"Name":"Recon Infantry Recon Battalion, 201st Pesht Assault Team, 3rd Proserpina Hussars","GroupName":null,"Class":"Recon Infantry","Variant":"Recon Battalion, 201st Pesht Assault Team, 3rd Proserpina Hussars","Tonnage":11,"BattleValue":22,"Technology":{"Id":1,"Name":"Inner Sphere","Image":null,"SortOrder":0},"Cost":0,"Rules":"Advanced","TROId":202,"TRO":"TR3085","RSId":253,"RS":"RS3085u-CE","EraIcon":"https://i.ibb.co/fr2Wdf0/era01-age-of-war-star-league.png","DateIntroduced":"2500","EraId":9,"EraStart":2005,"ImageUrl":"https://i.ibb.co/m4J0CzK/recon-infatnry-dcms.png","IsFeatured":true,"IsPublished":true,"Release":1.00,"Type":{"Id":21,"Name":"Infantry","Image":"Infantry.gif","SortOrder":3},"Role":{"Id":105,"Name":"Scout","Image":null,"SortOrder":6},"BFType":"CI","BFSize":1,"BFMove":"10\"h","BFTMM":2,"BFArmor":1,"BFStructure":1,"BFThreshold":0,"BFDamageShort":0,"BFDamageMedium":0,"BFDamageLong":0,"BFDamageExtreme":0,"BFOverheat":0,"BFPointValue":5,"BFAbilities":"CAR11","Skill":4,"FormatedTonnage":"11"}