{"Id":2804,"Name":"Satyr 4","GroupName":null,"Class":"Satyr","Variant":"4","Tonnage":4,"BattleValue":107,"Technology":{"Id":2,"Name":"Clan","Image":null,"SortOrder":0},"Cost":691530,"Rules":"Standard","TROId":229,"TRO":"TR3060","RSId":222,"RS":"RS3060u","EraIcon":"https://i.ibb.co/4jf2wfz/era05-jihad.png","DateIntroduced":"3074","EraId":14,"EraStart":3068,"ImageUrl":"https://i.ibb.co/Z64ZczD/satyr-3060.png","IsFeatured":false,"IsPublished":true,"Release":1.00,"Type":{"Id":23,"Name":"Protomech","Image":"NonStandard.gif","SortOrder":5},"Role":{"Id":106,"Name":"Striker","Image":null,"SortOrder":8},"BFType":"PM","BFSize":1,"BFMove":"14\"","BFTMM":3,"BFArmor":0,"BFStructure":1,"BFThreshold":0,"BFDamageShort":0,"BFDamageShortMin":true,"BFDamageMedium":0,"BFDamageMediumMin":true,"BFDamageLong":0,"BFDamageLongMin":false,"BFDamageExtreme":0,"BFDamageExtemeMin":false,"BFOverheat":0,"BFPointValue":7,"BFAbilities":"LTAG","Skill":4,"FormatedTonnage":"4"}