{"Id":2869,"Name":"Seraph C-SRP-O Invictus","GroupName":null,"Class":"Seraph","Variant":"C-SRP-O Invictus","Tonnage":85,"BattleValue":1794,"Technology":{"Id":1,"Name":"Inner Sphere","Image":null,"SortOrder":0},"Cost":21368772,"Rules":"Standard","TROId":463,"TRO":"TR:J","RSId":534,"RS":"RS:J","EraIcon":"https://i.ibb.co/4jf2wfz/era05-jihad.png","DateIntroduced":"3069","EraId":14,"EraStart":3068,"ImageUrl":"https://i.ibb.co/CB6LYYV/seraph-invictus-3075.png","IsFeatured":true,"IsPublished":true,"Release":1.00,"Type":{"Id":18,"Name":"BattleMech","Image":"BattleMech.gif","SortOrder":0},"Role":{"Id":108,"Name":"Juggernaut","Image":null,"SortOrder":3},"BFType":"BM","BFSize":4,"BFMove":"6\"","BFTMM":1,"BFArmor":9,"BFStructure":5,"BFThreshold":0,"BFDamageShort":5,"BFDamageShortMin":false,"BFDamageMedium":4,"BFDamageMediumMin":false,"BFDamageLong":3,"BFDamageLongMin":false,"BFDamageExtreme":0,"BFDamageExtemeMin":false,"BFOverheat":1,"BFPointValue":52,"BFAbilities":"C3I,CASE,IF1,MEL,MHQ2,OMNI,SAW,TSM","Skill":4,"FormatedTonnage":"85"}