{"Id":3454,"Name":"Von Luckner Heavy Tank VNL-K75N","GroupName":null,"Class":"Von Luckner Heavy Tank","Variant":"VNL-K75N","Tonnage":75,"BattleValue":1350,"Technology":{"Id":1,"Name":"Inner Sphere","Image":null,"SortOrder":0},"Cost":4134375,"Rules":"Standard","TROId":523,"TRO":"RG32","RSId":523,"RS":"RG32","EraIcon":"https://i.ibb.co/QjhjKwr/era04-civil-war.png","DateIntroduced":"3062","EraId":247,"EraStart":3062,"ImageUrl":"https://i.ibb.co/ZgtkBW5/von-luckner-heavy-tank-rg.png","IsFeatured":false,"IsPublished":true,"Release":1.00,"Type":{"Id":19,"Name":"Combat Vehicle","Image":"CombatVehicle.gif","SortOrder":1},"Role":{"Id":108,"Name":"Juggernaut","Image":null,"SortOrder":3},"BFType":"CV","BFSize":3,"BFMove":"6\"t","BFTMM":1,"BFArmor":6,"BFStructure":4,"BFThreshold":0,"BFDamageShort":7,"BFDamageShortMin":false,"BFDamageMedium":6,"BFDamageMediumMin":false,"BFDamageLong":0,"BFDamageLongMin":false,"BFDamageExtreme":0,"BFDamageExtemeMin":false,"BFOverheat":0,"BFPointValue":36,"BFAbilities":"SRCH,TUR(5/5/-)","Skill":4,"FormatedTonnage":"75"}