{"Id":3659,"Name":"Zugvogel Omni Support Aircraft E","GroupName":null,"Class":"Zugvogel Omni Support Aircraft","Variant":"E","Tonnage":200,"BattleValue":1028,"Technology":{"Id":1,"Name":"Inner Sphere","Image":null,"SortOrder":0},"Cost":16381250,"Rules":"Standard","TROId":202,"TRO":"TR3085","RSId":253,"RS":"RS3085u-CE","EraIcon":"https://i.ibb.co/VtCdwyP/era8-10-republic-dark-age.png","DateIntroduced":"3086","EraId":15,"EraStart":3081,"ImageUrl":"https://i.ibb.co/Sy97CcW/zugvogel-3085.png","IsFeatured":false,"IsPublished":true,"Release":1.00,"Type":{"Id":24,"Name":"Support Vehicle","Image":"NonStandard.gif","SortOrder":6},"Role":{"Id":117,"Name":"Attack","Image":null,"SortOrder":21},"BFType":"SV","BFSize":3,"BFMove":"4a","BFTMM":0,"BFArmor":7,"BFStructure":2,"BFThreshold":3,"BFDamageShort":2,"BFDamageMedium":1,"BFDamageLong":1,"BFDamageExtreme":0,"BFOverheat":0,"BFPointValue":22,"BFAbilities":"AFC,AMS,ATMO,ECM,IT48,LG,REAR1/1/1/-","Skill":4,"FormatedTonnage":"200"}