{"Id":4563,"Name":"Mad Cat III X","GroupName":null,"Class":"Mad Cat III","Variant":"X","Tonnage":55,"BattleValue":2232,"Technology":{"Id":2,"Name":"Clan","Image":null,"SortOrder":0},"Cost":13319925,"Rules":"Experimental","TROId":263,"TRO":"XTR: Clans","RSId":263,"RS":"XTR: Clans","EraIcon":"https://i.ibb.co/4jf2wfz/era05-jihad.png","DateIntroduced":"3076","EraId":14,"EraStart":3068,"ImageUrl":"https://i.ibb.co/yPWdWN8/mad-cat-iii-proto.png","IsFeatured":true,"IsPublished":true,"Release":1.00,"Type":{"Id":18,"Name":"BattleMech","Image":"BattleMech.gif","SortOrder":0},"Role":{"Id":110,"Name":"Missile Boat","Image":null,"SortOrder":4},"BFType":"BM","BFSize":2,"BFMove":"12\"","BFTMM":2,"BFArmor":6,"BFStructure":3,"BFThreshold":0,"BFDamageShort":6,"BFDamageMedium":5,"BFDamageLong":4,"BFDamageExtreme":0,"BFOverheat":1,"BFPointValue":50,"BFAbilities":"CASE,CR,IF3","Skill":4,"FormatedTonnage":"55"}