{"Id":4727,"Name":"Ninja-To NJT-3","GroupName":null,"Class":"Ninja-To","Variant":"NJT-3","Tonnage":65,"BattleValue":1605,"Technology":{"Id":1,"Name":"Inner Sphere","Image":null,"SortOrder":0},"Cost":15915900,"Rules":"Standard","TROId":246,"TRO":"TR3067","RSId":367,"RS":"RS3067u","EraIcon":"https://i.ibb.co/4jf2wfz/era7-jihad.png","DateIntroduced":"3068","EraId":14,"EraStart":3068,"ImageUrl":"https://i.ibb.co/NZsnZFQ/ninja-to-3067.png","IsFeatured":false,"IsPublished":true,"Release":1.20,"Type":{"Id":18,"Name":"BattleMech","Image":"BattleMech.gif","SortOrder":0},"Role":{"Id":107,"Name":"Skirmisher","Image":null,"SortOrder":5},"BFType":"BM","BFSize":3,"BFMove":"12\"","BFTMM":2,"BFArmor":7,"BFStructure":3,"BFThreshold":0,"BFDamageShort":3,"BFDamageMedium":3,"BFDamageLong":2,"BFDamageExtreme":0,"BFOverheat":0,"BFPointValue":40,"BFAbilities":"C3S,ENE,MHQ1","Skill":4,"FormatedTonnage":"65"}