{"Id":5463,"Name":"Anti-\u0027Mech Jump Infantry  ","GroupName":null,"Class":"Anti-\u0027Mech Jump Infantry","Variant":" ","Tonnage":4,"BattleValue":158,"Technology":{"Id":1,"Name":"Inner Sphere","Image":null,"SortOrder":0},"Cost":0,"Rules":"Standard","TROId":202,"TRO":"TR:3085","RSId":253,"RS":"RS:3085u-CE","EraIcon":"https://i.ibb.co/fr2Wdf0/era01-age-of-war-star-league.png","DateIntroduced":"2600","EraId":10,"EraStart":2571,"ImageUrl":"https://i.ibb.co/xj8D4q6/anti-mech-jump-infantry-gbd.png","IsFeatured":true,"IsPublished":true,"Release":1.00,"Type":{"Id":21,"Name":"Infantry","Image":"Infantry.gif","SortOrder":3},"Role":{"Id":112,"Name":"Ambusher","Image":null,"SortOrder":1},"BFType":"CI","BFSize":1,"BFMove":"6\"j","BFTMM":1,"BFArmor":2,"BFStructure":1,"BFThreshold":0,"BFDamageShort":1,"BFDamageShortMin":false,"BFDamageMedium":1,"BFDamageMediumMin":false,"BFDamageLong":0,"BFDamageLongMin":false,"BFDamageExtreme":0,"BFDamageExtemeMin":false,"BFOverheat":0,"BFPointValue":11,"BFAbilities":"AM,CAR4","Skill":4,"FormatedTonnage":"4"}