{"Id":5786,"Name":"Hawk Moth Gunship \"Verwandlung\"","GroupName":null,"Class":"Hawk Moth Gunship","Variant":"\"Verwandlung\"","Tonnage":25,"BattleValue":749,"Technology":{"Id":1,"Name":"Inner Sphere","Image":null,"SortOrder":0},"Cost":0,"Rules":"Experimental","TROId":369,"TRO":"XTR: Most Wanted","RSId":369,"RS":"XTR: Most Wanted","EraIcon":"https://i.ibb.co/VtCdwyP/era06-republic-dark-age.png","DateIntroduced":"3081","EraId":15,"EraStart":3081,"ImageUrl":"https://i.ibb.co/smkqH99/hawk-moth-3060.png","IsFeatured":true,"IsPublished":true,"Release":1.00,"Type":{"Id":19,"Name":"Combat Vehicle","Image":"CombatVehicle.gif","SortOrder":1},"Role":{"Id":106,"Name":"Striker","Image":null,"SortOrder":8},"BFType":"CV","BFSize":1,"BFMove":"16\"v","BFTMM":3,"BFArmor":1,"BFStructure":3,"BFThreshold":0,"BFDamageShort":2,"BFDamageShortMin":false,"BFDamageMedium":2,"BFDamageMediumMin":false,"BFDamageLong":0,"BFDamageLongMin":false,"BFDamageExtreme":0,"BFDamageExtemeMin":false,"BFOverheat":0,"BFPointValue":21,"BFAbilities":"ATMO,FC,SRCH,TUR(2/2/-)","Skill":4,"FormatedTonnage":"25"}