{"Id":6277,"Name":"Loki Mk II (Hel) Prime","GroupName":null,"Class":"Loki Mk II (Hel)","Variant":"Prime","Tonnage":65,"BattleValue":2189,"Technology":{"Id":2,"Name":"Clan","Image":null,"SortOrder":0},"Cost":0,"Rules":"Standard","TROId":514,"TRO":"TR:DA","RSId":535,"RS":"RS:DA","EraIcon":"https://i.ibb.co/VtCdwyP/era06-republic-dark-age.png","DateIntroduced":"3121","EraId":254,"EraStart":3101,"ImageUrl":"https://i.ibb.co/hd3VgkB/loki-mk-ii-hel-3150.png","IsFeatured":true,"IsPublished":true,"Release":1.00,"Type":{"Id":18,"Name":"BattleMech","Image":"BattleMech.gif","SortOrder":0},"Role":{"Id":111,"Name":"Sniper","Image":null,"SortOrder":7},"BFType":"BM","BFSize":3,"BFMove":"8\"","BFTMM":1,"BFArmor":6,"BFStructure":4,"BFThreshold":0,"BFDamageShort":5,"BFDamageShortMin":false,"BFDamageMedium":6,"BFDamageMediumMin":false,"BFDamageLong":5,"BFDamageLongMin":false,"BFDamageExtreme":0,"BFDamageExtemeMin":false,"BFOverheat":0,"BFPointValue":42,"BFAbilities":"CASE,OMNI","Skill":4,"FormatedTonnage":"65"}