{"Id":6440,"Name":"Shun Transport VTOL","GroupName":null,"Class":"Shun Transport VTOL","Variant":"","Tonnage":40,"BattleValue":499,"Technology":{"Id":1,"Name":"Inner Sphere","Image":null,"SortOrder":0},"Cost":4319778,"Rules":"Standard","TROId":441,"TRO":"TR3150","RSId":439,"RS":"RS3145u","EraIcon":"https://i.ibb.co/VtCdwyP/era06-republic-dark-age.png","DateIntroduced":"3122","EraId":254,"EraStart":3101,"ImageUrl":"https://i.ibb.co/j5hZrTW/shun-3150.png","IsFeatured":true,"IsPublished":true,"Release":1.00,"Type":{"Id":19,"Name":"Combat Vehicle","Image":"CombatVehicle.gif","SortOrder":1},"Role":{"Id":105,"Name":"Scout","Image":null,"SortOrder":6},"BFType":"CV","BFSize":2,"BFMove":"14\"v","BFTMM":3,"BFArmor":4,"BFStructure":2,"BFThreshold":0,"BFDamageShort":1,"BFDamageShortMin":false,"BFDamageMedium":1,"BFDamageMediumMin":false,"BFDamageLong":0,"BFDamageLongMin":false,"BFDamageExtreme":0,"BFDamageExtemeMin":false,"BFOverheat":0,"BFPointValue":27,"BFAbilities":"ATMO,ECM,IT12,SRCH,TAG,STL","Skill":4,"FormatedTonnage":"40"}