{"Id":7685,"Name":"Emperor EMP-6A-EC","GroupName":null,"Class":"Emperor","Variant":"EMP-6A-EC","Tonnage":90,"BattleValue":2165,"Technology":{"Id":3,"Name":"Mixed","Image":null,"SortOrder":0},"Cost":19017100,"Rules":"Experimental","TROId":445,"TRO":"TRGC","RSId":445,"RS":"TRGC","EraIcon":"https://i.ibb.co/MB09bVm/era3-4-succession-wars.png","DateIntroduced":"2826","EraId":11,"EraStart":2781,"ImageUrl":"https://i.ibb.co/wBNVpfR/emperor-3058u.png","IsFeatured":false,"IsPublished":true,"Release":1.00,"Type":{"Id":18,"Name":"BattleMech","Image":"BattleMech.gif","SortOrder":0},"Role":{"Id":111,"Name":"Sniper","Image":null,"SortOrder":7},"BFType":"BM","BFSize":4,"BFMove":"6\"j","BFTMM":1,"BFArmor":9,"BFStructure":4,"BFThreshold":0,"BFDamageShort":4,"BFDamageMedium":4,"BFDamageLong":3,"BFDamageExtreme":0,"BFOverheat":2,"BFPointValue":44,"BFAbilities":"CASE,FLK1/1/1","Skill":4,"FormatedTonnage":"90"}