{"Id":798,"Name":"Daikyu DAI-01 (Tabitha)","GroupName":null,"Class":"Daikyu","Variant":"DAI-01 (Tabitha)","Tonnage":70,"BattleValue":1804,"Technology":{"Id":3,"Name":"Mixed","Image":null,"SortOrder":0},"Cost":16320907,"Rules":"Experimental","TROId":236,"TRO":"RSUM","RSId":236,"RS":"RSUM","EraIcon":"https://i.ibb.co/QjhjKwr/era04-civil-war.png","DateIntroduced":"3064","EraId":247,"EraStart":3062,"ImageUrl":"https://i.ibb.co/tP9svkt/daikyu-3055u.png","IsFeatured":false,"IsPublished":true,"Release":1.00,"Type":{"Id":18,"Name":"BattleMech","Image":"BattleMech.gif","SortOrder":0},"Role":{"Id":111,"Name":"Sniper","Image":null,"SortOrder":7},"BFType":"BM","BFSize":3,"BFMove":"10\"","BFTMM":2,"BFArmor":7,"BFStructure":3,"BFThreshold":0,"BFDamageShort":3,"BFDamageMedium":3,"BFDamageLong":3,"BFDamageExtreme":0,"BFOverheat":0,"BFPointValue":38,"BFAbilities":"CASE,FLK1/1/1","Skill":4,"FormatedTonnage":"70"}