{"Id":8289,"Name":"Griffin GRF-1DS (Almstedt)","GroupName":null,"Class":"Griffin","Variant":"GRF-1DS (Almstedt)","Tonnage":55,"BattleValue":0,"Technology":{"Id":1,"Name":"Inner Sphere","Image":null,"SortOrder":0},"Cost":0,"Rules":"Standard","TROId":488,"TRO":"CM:Kurita","RSId":192,"RS":"None","EraIcon":"https://i.ibb.co/k6ySqKN/era03-clan-invasion.png","DateIntroduced":"Unknown","EraId":13,"EraStart":3050,"ImageUrl":"https://i.ibb.co/JRfrnbh/griffin-rg.png","IsFeatured":true,"IsPublished":true,"Release":1.00,"Type":{"Id":18,"Name":"BattleMech","Image":"BattleMech.gif","SortOrder":0},"Role":{"Id":107,"Name":"Skirmisher","Image":null,"SortOrder":5},"BFType":"BM","BFSize":2,"BFMove":"10\"j","BFTMM":2,"BFArmor":5,"BFStructure":3,"BFThreshold":0,"BFDamageShort":2,"BFDamageShortMin":false,"BFDamageMedium":2,"BFDamageMediumMin":false,"BFDamageLong":1,"BFDamageLongMin":false,"BFDamageExtreme":0,"BFDamageExtemeMin":false,"BFOverheat":0,"BFPointValue":29,"BFAbilities":"CASE,IF1,MEL","Skill":4,"FormatedTonnage":"55"}