{"Id":8915,"Name":"Kage Light Battle Armor [Laser] (Sqd6)","GroupName":null,"Class":"Kage Light Battle Armor","Variant":"[Laser] (Sqd6)","Tonnage":0.75,"BattleValue":194,"Technology":{"Id":1,"Name":"Inner Sphere","Image":null,"SortOrder":0},"Cost":0,"Rules":"Standard","TROId":240,"TRO":"TR3058U","RSId":255,"RS":"RS3058Uu-C","EraIcon":"https://i.ibb.co/k6ySqKN/era03-clan-invasion.png","DateIntroduced":"3056","EraId":13,"EraStart":3050,"ImageUrl":"https://i.ibb.co/6n835v6/kage-3058u.png","IsFeatured":false,"IsPublished":true,"Release":1.00,"Type":{"Id":21,"Name":"Infantry","Image":"Infantry.gif","SortOrder":3},"Role":{"Id":105,"Name":"Scout","Image":null,"SortOrder":6},"BFType":"BA","BFSize":1,"BFMove":"8\"j","BFTMM":1,"BFArmor":1,"BFStructure":2,"BFThreshold":0,"BFDamageShort":1,"BFDamageShortMin":false,"BFDamageMedium":0,"BFDamageMediumMin":false,"BFDamageLong":0,"BFDamageLongMin":false,"BFDamageExtreme":0,"BFDamageExtemeMin":false,"BFOverheat":0,"BFPointValue":11,"BFAbilities":"AM,CAR6,MEC,STL","Skill":4,"FormatedTonnage":"0.8"}