{"Id":9042,"Name":"Sylph Battle Armor (Enhanced) (Sqd6)","GroupName":null,"Class":"Sylph Battle Armor","Variant":"(Enhanced) (Sqd6)","Tonnage":0.8,"BattleValue":284,"Technology":{"Id":2,"Name":"Clan","Image":null,"SortOrder":0},"Cost":0,"Rules":"Advanced","TROId":260,"TRO":"TRProto","RSId":428,"RS":"RSProto","EraIcon":"https://i.ibb.co/VtCdwyP/era06-republic-dark-age.png","DateIntroduced":"3085","EraId":15,"EraStart":3081,"ImageUrl":"https://i.ibb.co/Hg5F7ZH/sylph-proto.png","IsFeatured":true,"IsPublished":true,"Release":1.10,"Type":{"Id":21,"Name":"Infantry","Image":"Infantry.gif","SortOrder":3},"Role":{"Id":105,"Name":"Scout","Image":null,"SortOrder":6},"BFType":"BA","BFSize":1,"BFMove":"10\"f","BFTMM":2,"BFArmor":1,"BFStructure":2,"BFThreshold":0,"BFDamageShort":2,"BFDamageShortMin":false,"BFDamageMedium":0,"BFDamageMediumMin":false,"BFDamageLong":0,"BFDamageLongMin":false,"BFDamageExtreme":0,"BFDamageExtemeMin":false,"BFOverheat":0,"BFPointValue":10,"BFAbilities":"AM,CAR6,MEC","Skill":4,"FormatedTonnage":"0.8"}