{"Id":9488,"Name":"Viper VP-5","GroupName":null,"Class":"Viper","Variant":"VP-5","Tonnage":70,"BattleValue":1539,"Technology":{"Id":1,"Name":"Inner Sphere","Image":null,"SortOrder":0},"Cost":0,"Rules":"Introductory","TROId":523,"TRO":"RG32","RSId":523,"RS":"RG32","EraIcon":"https://i.ibb.co/MB09bVm/era02-succession-wars.png","DateIntroduced":"2958","EraId":255,"EraStart":2901,"ImageUrl":"https://i.ibb.co/SsMzz1s/viper-rg.png","IsFeatured":false,"IsPublished":true,"Release":1.00,"Type":{"Id":18,"Name":"BattleMech","Image":"BattleMech.gif","SortOrder":0},"Role":{"Id":109,"Name":"Brawler","Image":null,"SortOrder":2},"BFType":"BM","BFSize":3,"BFMove":"8\"j","BFTMM":1,"BFArmor":7,"BFStructure":6,"BFThreshold":0,"BFDamageShort":3,"BFDamageShortMin":false,"BFDamageMedium":3,"BFDamageMediumMin":false,"BFDamageLong":0,"BFDamageLongMin":false,"BFDamageExtreme":0,"BFDamageExtemeMin":false,"BFOverheat":2,"BFPointValue":36,"BFAbilities":"ENE","Skill":4,"FormatedTonnage":"70"}